<?xml version="1.0" encoding="UTF-8" standalone="no"?>
<PSGAnnotation>
<SoftwareVersion>Compumedics</SoftwareVersion>
<EpochLength>30</EpochLength>
<ScoredEvents>
<ScoredEvent>
<EventType/>
<EventConcept>Recording Start Time</EventConcept>
<Start>0</Start>
<Duration>33840.0</Duration>
<ClockTime>00.00.00 21.06.47</ClockTime>
</ScoredEvent>
<ScoredEvent>
<EventType>Respiratory|Respiratory</EventType>
<EventConcept>SpO2 artifact|SpO2 artifact</EventConcept>
<Start>560.8</Start>
<Duration>207.5</Duration>
<SignalLocation>SaO2</SignalLocation>
</ScoredEvent>
<ScoredEvent>
<EventType>Respiratory|Respiratory</EventType>
<EventConcept>SpO2 artifact|SpO2 artifact</EventConcept>
<Start>871</Start>
<Duration>6</Duration>
<SignalLocation>SaO2</SignalLocation>
</ScoredEvent>
<ScoredEvent>
<EventType>Respiratory|Respiratory</EventType>
<EventConcept>SpO2 artifact|SpO2 artifact</EventConcept>
<Start>1338</Start>
<Duration>7</Duration>
<SignalLocation>SaO2</SignalLocation>
</ScoredEvent>
<ScoredEvent>
<EventType>Respiratory|Respiratory</EventType>
<EventConcept>SpO2 artifact|SpO2 artifact</EventConcept>
<Start>3034</Start>
<Duration>8</Duration>
<SignalLocation>SaO2</SignalLocation>
</ScoredEvent>
<ScoredEvent>
<EventType>Respiratory|Respiratory</EventType>
<EventConcept>SpO2 artifact|SpO2 artifact</EventConcept>
<Start>3895</Start>
<Duration>15</Duration>
<SignalLocation>SaO2</SignalLocation>
</ScoredEvent>
<ScoredEvent>
<EventType>Respiratory|Respiratory</EventType>
<EventConcept>SpO2 artifact|SpO2 artifact</EventConcept>
<Start>7202</Start>
<Duration>4</Duration>
<SignalLocation>SaO2</SignalLocation>
</ScoredEvent>
<ScoredEvent>
<EventType>Respiratory|Respiratory</EventType>
<EventConcept>SpO2 artifact|SpO2 artifact</EventConcept>
<Start>7216</Start>
<Duration>33</Duration>
<SignalLocation>SaO2</SignalLocation>
</ScoredEvent>
<ScoredEvent>
<EventType>Respiratory|Respiratory</EventType>
<EventConcept>SpO2 artifact|SpO2 artifact</EventConcept>
<Start>7262</Start>
<Duration>20</Duration>
<SignalLocation>SaO2</SignalLocation>
</ScoredEvent>
<ScoredEvent>
<EventType>Respiratory|Respiratory</EventType>
<EventConcept>SpO2 artifact|SpO2 artifact</EventConcept>
<Start>7296</Start>
<Duration>9</Duration>
<SignalLocation>SaO2</SignalLocation>
</ScoredEvent>
<ScoredEvent>
<EventType>Respiratory|Respiratory</EventType>
<EventConcept>SpO2 artifact|SpO2 artifact</EventConcept>
<Start>7317</Start>
<Duration>9</Duration>
<SignalLocation>SaO2</SignalLocation>
</ScoredEvent>
<ScoredEvent>
<EventType>Respiratory|Respiratory</EventType>
<EventConcept>SpO2 artifact|SpO2 artifact</EventConcept>
<Start>7408</Start>
<Duration>4</Duration>
<SignalLocation>SaO2</SignalLocation>
</ScoredEvent>
<ScoredEvent>
<EventType>Respiratory|Respiratory</EventType>
<EventConcept>SpO2 artifact|SpO2 artifact</EventConcept>
<Start>7565</Start>
<Duration>37</Duration>
<SignalLocation>SaO2</SignalLocation>
</ScoredEvent>
<ScoredEvent>
<EventType>Respiratory|Respiratory</EventType>
<EventConcept>SpO2 artifact|SpO2 artifact</EventConcept>
<Start>7616</Start>
<Duration>17</Duration>
<SignalLocation>SaO2</SignalLocation>
</ScoredEvent>
<ScoredEvent>
<EventType>Respiratory|Respiratory</EventType>
<EventConcept>SpO2 artifact|SpO2 artifact</EventConcept>
<Start>7649</Start>
<Duration>14</Duration>
<SignalLocation>SaO2</SignalLocation>
</ScoredEvent>
<ScoredEvent>
<EventType>Respiratory|Respiratory</EventType>
<EventConcept>SpO2 artifact|SpO2 artifact</EventConcept>
<Start>7730</Start>
<Duration>12</Duration>
<SignalLocation>SaO2</SignalLocation>
</ScoredEvent>
<ScoredEvent>
<EventType>Respiratory|Respiratory</EventType>
<EventConcept>SpO2 artifact|SpO2 artifact</EventConcept>
<Start>7787</Start>
<Duration>14</Duration>
<SignalLocation>SaO2</SignalLocation>
</ScoredEvent>
<ScoredEvent>
<EventType>Arousals|Arousals</EventType>
<EventConcept>Arousal resulting from respiratory effort|Arousal (RESP ARO)</EventConcept>
<Start>8032.6</Start>
<Duration>7.4</Duration>
<SignalLocation>C3</SignalLocation>
</ScoredEvent>
<ScoredEvent>
<EventType>Respiratory|Respiratory</EventType>
<EventConcept>Hypopnea|Hypopnea</EventConcept>
<Start>8192.8</Start>
<Duration>17.3</Duration>
<SignalLocation>ABDO EFFORT</SignalLocation>
</ScoredEvent>
<ScoredEvent>
<EventType>Respiratory|Respiratory</EventType>
<EventConcept>SpO2 desaturation|SpO2 desaturation</EventConcept>
<Start>8222.8</Start>
<Duration>17.3</Duration>
<SignalLocation>SaO2</SignalLocation>
<SpO2Nadir>94</SpO2Nadir>
<SpO2Baseline>96.0</SpO2Baseline>
</ScoredEvent>
<ScoredEvent>
<EventType>Respiratory|Respiratory</EventType>
<EventConcept>Hypopnea|Hypopnea</EventConcept>
<Start>8239</Start>
<Duration>14.2</Duration>
<SignalLocation>ABDO EFFORT</SignalLocation>
</ScoredEvent>
<ScoredEvent>
<EventType>Respiratory|Respiratory</EventType>
<EventConcept>SpO2 desaturation|SpO2 desaturation</EventConcept>
<Start>8269</Start>
<Duration>14.2</Duration>
<SignalLocation>SaO2</SignalLocation>
<SpO2Nadir>94</SpO2Nadir>
<SpO2Baseline>95.0</SpO2Baseline>
</ScoredEvent>
<ScoredEvent>
<EventType>Arousals|Arousals</EventType>
<EventConcept>Arousal resulting from respiratory effort|Arousal (RESP ARO)</EventConcept>
<Start>8353.5</Start>
<Duration>13.1</Duration>
<SignalLocation>C3</SignalLocation>
</ScoredEvent>
<ScoredEvent>
<EventType>Arousals|Arousals</EventType>
<EventConcept>Arousal resulting from respiratory effort|Arousal (RESP ARO)</EventConcept>
<Start>8400.9</Start>
<Duration>19.6</Duration>
<SignalLocation>C3</SignalLocation>
</ScoredEvent>
<ScoredEvent>
<EventType>Respiratory|Respiratory</EventType>
<EventConcept>Hypopnea|Hypopnea</EventConcept>
<Start>8463.7</Start>
<Duration>14.4</Duration>
<SignalLocation>ABDO EFFORT</SignalLocation>
</ScoredEvent>
<ScoredEvent>
<EventType>Respiratory|Respiratory</EventType>
<EventConcept>SpO2 desaturation|SpO2 desaturation</EventConcept>
<Start>8493.7</Start>
<Duration>14.4</Duration>
<SignalLocation>SaO2</SignalLocation>
<SpO2Nadir>93</SpO2Nadir>
<SpO2Baseline>95.0</SpO2Baseline>
</ScoredEvent>
<ScoredEvent>
<EventType>Arousals|Arousals</EventType>
<EventConcept>Spontaneous arousal|Arousal (SPON ARO)</EventConcept>
<Start>9620.2</Start>
<Duration>9.7</Duration>
<SignalLocation>C3</SignalLocation>
</ScoredEvent>
<ScoredEvent>
<EventType>Respiratory|Respiratory</EventType>
<EventConcept>SpO2 artifact|SpO2 artifact</EventConcept>
<Start>9665</Start>
<Duration>18</Duration>
<SignalLocation>SaO2</SignalLocation>
</ScoredEvent>
<ScoredEvent>
<EventType>Respiratory|Respiratory</EventType>
<EventConcept>SpO2 artifact|SpO2 artifact</EventConcept>
<Start>9813.1</Start>
<Duration>54.1</Duration>
<SignalLocation>SaO2</SignalLocation>
</ScoredEvent>
<ScoredEvent>
<EventType>Respiratory|Respiratory</EventType>
<EventConcept>SpO2 artifact|SpO2 artifact</EventConcept>
<Start>9926</Start>
<Duration>4</Duration>
<SignalLocation>SaO2</SignalLocation>
</ScoredEvent>
<ScoredEvent>
<EventType>Respiratory|Respiratory</EventType>
<EventConcept>SpO2 artifact|SpO2 artifact</EventConcept>
<Start>9985</Start>
<Duration>16</Duration>
<SignalLocation>SaO2</SignalLocation>
</ScoredEvent>
<ScoredEvent>
<EventType>Respiratory|Respiratory</EventType>
<EventConcept>SpO2 artifact|SpO2 artifact</EventConcept>
<Start>10108</Start>
<Duration>35</Duration>
<SignalLocation>SaO2</SignalLocation>
</ScoredEvent>
<ScoredEvent>
<EventType>Respiratory|Respiratory</EventType>
<EventConcept>SpO2 artifact|SpO2 artifact</EventConcept>
<Start>10163</Start>
<Duration>11</Duration>
<SignalLocation>SaO2</SignalLocation>
</ScoredEvent>
<ScoredEvent>
<EventType>Respiratory|Respiratory</EventType>
<EventConcept>SpO2 artifact|SpO2 artifact</EventConcept>
<Start>10362</Start>
<Duration>16</Duration>
<SignalLocation>SaO2</SignalLocation>
</ScoredEvent>
<ScoredEvent>
<EventType>Respiratory|Respiratory</EventType>
<EventConcept>SpO2 artifact|SpO2 artifact</EventConcept>
<Start>10388</Start>
<Duration>12</Duration>
<SignalLocation>SaO2</SignalLocation>
</ScoredEvent>
<ScoredEvent>
<EventType>Arousals|Arousals</EventType>
<EventConcept>Arousal resulting from respiratory effort|Arousal (RESP ARO)</EventConcept>
<Start>10573.5</Start>
<Duration>6.2</Duration>
<SignalLocation>C3</SignalLocation>
</ScoredEvent>
<ScoredEvent>
<EventType>Respiratory|Respiratory</EventType>
<EventConcept>Hypopnea|Hypopnea</EventConcept>
<Start>10590.9</Start>
<Duration>29.5</Duration>
<SignalLocation>ABDO EFFORT</SignalLocation>
</ScoredEvent>
<ScoredEvent>
<EventType>Respiratory|Respiratory</EventType>
<EventConcept>SpO2 desaturation|SpO2 desaturation</EventConcept>
<Start>10620.9</Start>
<Duration>29.5</Duration>
<SignalLocation>SaO2</SignalLocation>
<SpO2Nadir>93</SpO2Nadir>
<SpO2Baseline>95.0</SpO2Baseline>
</ScoredEvent>
<ScoredEvent>
<EventType>Arousals|Arousals</EventType>
<EventConcept>Spontaneous arousal|Arousal (SPON ARO)</EventConcept>
<Start>10836.4</Start>
<Duration>4.7</Duration>
<SignalLocation>C3</SignalLocation>
</ScoredEvent>
<ScoredEvent>
<EventType>Respiratory|Respiratory</EventType>
<EventConcept>Obstructive apnea|Obstructive Apnea</EventConcept>
<Start>11029.4</Start>
<Duration>18.9</Duration>
<SignalLocation>ABDO EFFORT</SignalLocation>
</ScoredEvent>
<ScoredEvent>
<EventType>Respiratory|Respiratory</EventType>
<EventConcept>Hypopnea|Hypopnea</EventConcept>
<Start>11068.7</Start>
<Duration>25.4</Duration>
<SignalLocation>ABDO EFFORT</SignalLocation>
</ScoredEvent>
<ScoredEvent>
<EventType>Respiratory|Respiratory</EventType>
<EventConcept>Obstructive apnea|Obstructive Apnea</EventConcept>
<Start>11286.7</Start>
<Duration>10.1</Duration>
<SignalLocation>ABDO EFFORT</SignalLocation>
</ScoredEvent>
<ScoredEvent>
<EventType>Respiratory|Respiratory</EventType>
<EventConcept>Hypopnea|Hypopnea</EventConcept>
<Start>11331.5</Start>
<Duration>39.6</Duration>
<SignalLocation>ABDO EFFORT</SignalLocation>
</ScoredEvent>
<ScoredEvent>
<EventType>Respiratory|Respiratory</EventType>
<EventConcept>SpO2 desaturation|SpO2 desaturation</EventConcept>
<Start>11361.5</Start>
<Duration>39.6</Duration>
<SignalLocation>SaO2</SignalLocation>
<SpO2Nadir>93</SpO2Nadir>
<SpO2Baseline>95.0</SpO2Baseline>
</ScoredEvent>
<ScoredEvent>
<EventType>Respiratory|Respiratory</EventType>
<EventConcept>Hypopnea|Hypopnea</EventConcept>
<Start>11460.6</Start>
<Duration>33.3</Duration>
<SignalLocation>ABDO EFFORT</SignalLocation>
</ScoredEvent>
<ScoredEvent>
<EventType>Respiratory|Respiratory</EventType>
<EventConcept>SpO2 desaturation|SpO2 desaturation</EventConcept>
<Start>11490.6</Start>
<Duration>33.3</Duration>
<SignalLocation>SaO2</SignalLocation>
<SpO2Nadir>91</SpO2Nadir>
<SpO2Baseline>95.0</SpO2Baseline>
</ScoredEvent>
<ScoredEvent>
<EventType>Respiratory|Respiratory</EventType>
<EventConcept>Hypopnea|Hypopnea</EventConcept>
<Start>11515.5</Start>
<Duration>19.4</Duration>
<SignalLocation>ABDO EFFORT</SignalLocation>
</ScoredEvent>
<ScoredEvent>
<EventType>Respiratory|Respiratory</EventType>
<EventConcept>SpO2 desaturation|SpO2 desaturation</EventConcept>
<Start>11545.5</Start>
<Duration>19.4</Duration>
<SignalLocation>SaO2</SignalLocation>
<SpO2Nadir>92</SpO2Nadir>
<SpO2Baseline>95.0</SpO2Baseline>
</ScoredEvent>
<ScoredEvent>
<EventType>Respiratory|Respiratory</EventType>
<EventConcept>Hypopnea|Hypopnea</EventConcept>
<Start>11550.2</Start>
<Duration>17.9</Duration>
<SignalLocation>ABDO EFFORT</SignalLocation>
</ScoredEvent>
<ScoredEvent>
<EventType>Respiratory|Respiratory</EventType>
<EventConcept>SpO2 desaturation|SpO2 desaturation</EventConcept>
<Start>11580.2</Start>
<Duration>17.9</Duration>
<SignalLocation>SaO2</SignalLocation>
<SpO2Nadir>93</SpO2Nadir>
<SpO2Baseline>94.0</SpO2Baseline>
</ScoredEvent>
<ScoredEvent>
<EventType>Respiratory|Respiratory</EventType>
<EventConcept>Obstructive apnea|Obstructive Apnea</EventConcept>
<Start>11651.6</Start>
<Duration>15</Duration>
<SignalLocation>ABDO EFFORT</SignalLocation>
</ScoredEvent>
<ScoredEvent>
<EventType>Respiratory|Respiratory</EventType>
<EventConcept>SpO2 desaturation|SpO2 desaturation</EventConcept>
<Start>11681.6</Start>
<Duration>15</Duration>
<SignalLocation>SaO2</SignalLocation>
<SpO2Nadir>91</SpO2Nadir>
<SpO2Baseline>95.0</SpO2Baseline>
</ScoredEvent>
<ScoredEvent>
<EventType>Respiratory|Respiratory</EventType>
<EventConcept>Hypopnea|Hypopnea</EventConcept>
<Start>11697.5</Start>
<Duration>24.8</Duration>
<SignalLocation>ABDO EFFORT</SignalLocation>
</ScoredEvent>
<ScoredEvent>
<EventType>Respiratory|Respiratory</EventType>
<EventConcept>SpO2 desaturation|SpO2 desaturation</EventConcept>
<Start>11727.5</Start>
<Duration>24.8</Duration>
<SignalLocation>SaO2</SignalLocation>
<SpO2Nadir>91</SpO2Nadir>
<SpO2Baseline>95.0</SpO2Baseline>
</ScoredEvent>
<ScoredEvent>
<EventType>Respiratory|Respiratory</EventType>
<EventConcept>Hypopnea|Hypopnea</EventConcept>
<Start>11747.2</Start>
<Duration>20.9</Duration>
<SignalLocation>ABDO EFFORT</SignalLocation>
</ScoredEvent>
<ScoredEvent>
<EventType>Respiratory|Respiratory</EventType>
<EventConcept>SpO2 desaturation|SpO2 desaturation</EventConcept>
<Start>11777.2</Start>
<Duration>20.9</Duration>
<SignalLocation>SaO2</SignalLocation>
<SpO2Nadir>93</SpO2Nadir>
<SpO2Baseline>96.0</SpO2Baseline>
</ScoredEvent>
<ScoredEvent>
<EventType>Respiratory|Respiratory</EventType>
<EventConcept>Hypopnea|Hypopnea</EventConcept>
<Start>11786</Start>
<Duration>17.4</Duration>
<SignalLocation>ABDO EFFORT</SignalLocation>
</ScoredEvent>
<ScoredEvent>
<EventType>Respiratory|Respiratory</EventType>
<EventConcept>SpO2 desaturation|SpO2 desaturation</EventConcept>
<Start>11816</Start>
<Duration>17.4</Duration>
<SignalLocation>SaO2</SignalLocation>
<SpO2Nadir>93</SpO2Nadir>
<SpO2Baseline>94.0</SpO2Baseline>
</ScoredEvent>
<ScoredEvent>
<EventType>Respiratory|Respiratory</EventType>
<EventConcept>Hypopnea|Hypopnea</EventConcept>
<Start>11830.6</Start>
<Duration>26.4</Duration>
<SignalLocation>ABDO EFFORT</SignalLocation>
</ScoredEvent>
<ScoredEvent>
<EventType>Arousals|Arousals</EventType>
<EventConcept>Spontaneous arousal|Arousal (SPON ARO)</EventConcept>
<Start>11858.9</Start>
<Duration>5.8</Duration>
<SignalLocation>C3</SignalLocation>
</ScoredEvent>
<ScoredEvent>
<EventType>Respiratory|Respiratory</EventType>
<EventConcept>SpO2 desaturation|SpO2 desaturation</EventConcept>
<Start>11860.6</Start>
<Duration>26.4</Duration>
<SignalLocation>SaO2</SignalLocation>
<SpO2Nadir>91</SpO2Nadir>
<SpO2Baseline>95.0</SpO2Baseline>
</ScoredEvent>
<ScoredEvent>
<EventType>Respiratory|Respiratory</EventType>
<EventConcept>Hypopnea|Hypopnea</EventConcept>
<Start>11885.1</Start>
<Duration>25.5</Duration>
<SignalLocation>ABDO EFFORT</SignalLocation>
</ScoredEvent>
<ScoredEvent>
<EventType>Respiratory|Respiratory</EventType>
<EventConcept>SpO2 desaturation|SpO2 desaturation</EventConcept>
<Start>11915.1</Start>
<Duration>25.5</Duration>
<SignalLocation>SaO2</SignalLocation>
<SpO2Nadir>94</SpO2Nadir>
<SpO2Baseline>96.0</SpO2Baseline>
</ScoredEvent>
<ScoredEvent>
<EventType>Respiratory|Respiratory</EventType>
<EventConcept>Obstructive apnea|Obstructive Apnea</EventConcept>
<Start>11942.4</Start>
<Duration>27.6</Duration>
<SignalLocation>ABDO EFFORT</SignalLocation>
</ScoredEvent>
<ScoredEvent>
<EventType>Arousals|Arousals</EventType>
<EventConcept>Arousal resulting from respiratory effort|Arousal (RESP ARO)</EventConcept>
<Start>11970.9</Start>
<Duration>25.5</Duration>
<SignalLocation>C3</SignalLocation>
</ScoredEvent>
<ScoredEvent>
<EventType>Respiratory|Respiratory</EventType>
<EventConcept>SpO2 desaturation|SpO2 desaturation</EventConcept>
<Start>11972.4</Start>
<Duration>27.6</Duration>
<SignalLocation>SaO2</SignalLocation>
<SpO2Nadir>89</SpO2Nadir>
<SpO2Baseline>97.0</SpO2Baseline>
</ScoredEvent>
<ScoredEvent>
<EventType>Limb Movement|Limb Movement</EventType>
<EventConcept>Limb movement - left|Limb Movement (Left)</EventConcept>
<Start>12502.9</Start>
<Duration>13.6</Duration>
<SignalLocation>L Leg</SignalLocation>
</ScoredEvent>
<ScoredEvent>
<EventType>Arousals|Arousals</EventType>
<EventConcept>Arousal resulting from respiratory effort|Arousal (RESP ARO)</EventConcept>
<Start>12506.3</Start>
<Duration>16.4</Duration>
<SignalLocation>C3</SignalLocation>
</ScoredEvent>
<ScoredEvent>
<EventType>Respiratory|Respiratory</EventType>
<EventConcept>SpO2 artifact|SpO2 artifact</EventConcept>
<Start>12591</Start>
<Duration>16</Duration>
<SignalLocation>SaO2</SignalLocation>
</ScoredEvent>
<ScoredEvent>
<EventType>Respiratory|Respiratory</EventType>
<EventConcept>SpO2 artifact|SpO2 artifact</EventConcept>
<Start>12642</Start>
<Duration>11</Duration>
<SignalLocation>SaO2</SignalLocation>
</ScoredEvent>
<ScoredEvent>
<EventType>Respiratory|Respiratory</EventType>
<EventConcept>Hypopnea|Hypopnea</EventConcept>
<Start>13335.7</Start>
<Duration>17</Duration>
<SignalLocation>ABDO EFFORT</SignalLocation>
</ScoredEvent>
<ScoredEvent>
<EventType>Respiratory|Respiratory</EventType>
<EventConcept>SpO2 desaturation|SpO2 desaturation</EventConcept>
<Start>13365.7</Start>
<Duration>17</Duration>
<SignalLocation>SaO2</SignalLocation>
<SpO2Nadir>94</SpO2Nadir>
<SpO2Baseline>96.0</SpO2Baseline>
</ScoredEvent>
<ScoredEvent>
<EventType>Respiratory|Respiratory</EventType>
<EventConcept>Hypopnea|Hypopnea</EventConcept>
<Start>13554.4</Start>
<Duration>14.1</Duration>
<SignalLocation>ABDO EFFORT</SignalLocation>
</ScoredEvent>
<ScoredEvent>
<EventType>Respiratory|Respiratory</EventType>
<EventConcept>SpO2 desaturation|SpO2 desaturation</EventConcept>
<Start>13584.4</Start>
<Duration>14.1</Duration>
<SignalLocation>SaO2</SignalLocation>
<SpO2Nadir>93</SpO2Nadir>
<SpO2Baseline>95.0</SpO2Baseline>
</ScoredEvent>
<ScoredEvent>
<EventType>Arousals|Arousals</EventType>
<EventConcept>Arousal resulting from respiratory effort|Arousal (RESP ARO)</EventConcept>
<Start>13608.4</Start>
<Duration>11.6</Duration>
<SignalLocation>C3</SignalLocation>
</ScoredEvent>
<ScoredEvent>
<EventType>Respiratory|Respiratory</EventType>
<EventConcept>Hypopnea|Hypopnea</EventConcept>
<Start>13736.8</Start>
<Duration>21</Duration>
<SignalLocation>ABDO EFFORT</SignalLocation>
</ScoredEvent>
<ScoredEvent>
<EventType>Respiratory|Respiratory</EventType>
<EventConcept>SpO2 desaturation|SpO2 desaturation</EventConcept>
<Start>13766.8</Start>
<Duration>21</Duration>
<SignalLocation>SaO2</SignalLocation>
<SpO2Nadir>96</SpO2Nadir>
<SpO2Baseline>97.0</SpO2Baseline>
</ScoredEvent>
<ScoredEvent>
<EventType>Respiratory|Respiratory</EventType>
<EventConcept>Hypopnea|Hypopnea</EventConcept>
<Start>14080.6</Start>
<Duration>13.8</Duration>
<SignalLocation>ABDO EFFORT</SignalLocation>
</ScoredEvent>
<ScoredEvent>
<EventType>Respiratory|Respiratory</EventType>
<EventConcept>SpO2 desaturation|SpO2 desaturation</EventConcept>
<Start>14110.6</Start>
<Duration>13.8</Duration>
<SignalLocation>SaO2</SignalLocation>
<SpO2Nadir>95</SpO2Nadir>
<SpO2Baseline>98.0</SpO2Baseline>
</ScoredEvent>
<ScoredEvent>
<EventType>Respiratory|Respiratory</EventType>
<EventConcept>Obstructive apnea|Obstructive Apnea</EventConcept>
<Start>14230.6</Start>
<Duration>20.7</Duration>
<SignalLocation>ABDO EFFORT</SignalLocation>
</ScoredEvent>
<ScoredEvent>
<EventType>Respiratory|Respiratory</EventType>
<EventConcept>SpO2 desaturation|SpO2 desaturation</EventConcept>
<Start>14260.6</Start>
<Duration>20.7</Duration>
<SignalLocation>SaO2</SignalLocation>
<SpO2Nadir>94</SpO2Nadir>
<SpO2Baseline>98.0</SpO2Baseline>
</ScoredEvent>
<ScoredEvent>
<EventType>Arousals|Arousals</EventType>
<EventConcept>Arousal resulting from respiratory effort|Arousal (RESP ARO)</EventConcept>
<Start>15287.4</Start>
<Duration>12.6</Duration>
<SignalLocation>C3</SignalLocation>
</ScoredEvent>
<ScoredEvent>
<EventType>Arousals|Arousals</EventType>
<EventConcept>Arousal resulting from respiratory effort|Arousal (RESP ARO)</EventConcept>
<Start>15364.5</Start>
<Duration>25.5</Duration>
<SignalLocation>C3</SignalLocation>
</ScoredEvent>
<ScoredEvent>
<EventType>Respiratory|Respiratory</EventType>
<EventConcept>Hypopnea|Hypopnea</EventConcept>
<Start>15546.4</Start>
<Duration>18.7</Duration>
<SignalLocation>ABDO EFFORT</SignalLocation>
</ScoredEvent>
<ScoredEvent>
<EventType>Respiratory|Respiratory</EventType>
<EventConcept>SpO2 desaturation|SpO2 desaturation</EventConcept>
<Start>15576.4</Start>
<Duration>18.7</Duration>
<SignalLocation>SaO2</SignalLocation>
<SpO2Nadir>94</SpO2Nadir>
<SpO2Baseline>95.0</SpO2Baseline>
</ScoredEvent>
<ScoredEvent>
<EventType>Arousals|Arousals</EventType>
<EventConcept>Arousal resulting from respiratory effort|Arousal (RESP ARO)</EventConcept>
<Start>15840.5</Start>
<Duration>29.1</Duration>
<SignalLocation>C3</SignalLocation>
</ScoredEvent>
<ScoredEvent>
<EventType>Respiratory|Respiratory</EventType>
<EventConcept>SpO2 artifact|SpO2 artifact</EventConcept>
<Start>15860</Start>
<Duration>4</Duration>
<SignalLocation>SaO2</SignalLocation>
</ScoredEvent>
<ScoredEvent>
<EventType>Arousals|Arousals</EventType>
<EventConcept>Arousal resulting from respiratory effort|Arousal (RESP ARO)</EventConcept>
<Start>16029.4</Start>
<Duration>4.8</Duration>
<SignalLocation>C3</SignalLocation>
</ScoredEvent>
<ScoredEvent>
<EventType>Respiratory|Respiratory</EventType>
<EventConcept>SpO2 artifact|SpO2 artifact</EventConcept>
<Start>16036</Start>
<Duration>5</Duration>
<SignalLocation>SaO2</SignalLocation>
</ScoredEvent>
<ScoredEvent>
<EventType>Arousals|Arousals</EventType>
<EventConcept>Arousal resulting from respiratory effort|Arousal (RESP ARO)</EventConcept>
<Start>16049.7</Start>
<Duration>7.9</Duration>
<SignalLocation>C3</SignalLocation>
</ScoredEvent>
<ScoredEvent>
<EventType>Arousals|Arousals</EventType>
<EventConcept>Arousal resulting from respiratory effort|Arousal (RESP ARO)</EventConcept>
<Start>16147.9</Start>
<Duration>6.3</Duration>
<SignalLocation>C3</SignalLocation>
</ScoredEvent>
<ScoredEvent>
<EventType>Respiratory|Respiratory</EventType>
<EventConcept>SpO2 artifact|SpO2 artifact</EventConcept>
<Start>16184</Start>
<Duration>33</Duration>
<SignalLocation>SaO2</SignalLocation>
</ScoredEvent>
<ScoredEvent>
<EventType>Respiratory|Respiratory</EventType>
<EventConcept>SpO2 artifact|SpO2 artifact</EventConcept>
<Start>16260</Start>
<Duration>15</Duration>
<SignalLocation>SaO2</SignalLocation>
</ScoredEvent>
<ScoredEvent>
<EventType>Respiratory|Respiratory</EventType>
<EventConcept>SpO2 artifact|SpO2 artifact</EventConcept>
<Start>16310</Start>
<Duration>23</Duration>
<SignalLocation>SaO2</SignalLocation>
</ScoredEvent>
<ScoredEvent>
<EventType>Respiratory|Respiratory</EventType>
<EventConcept>SpO2 artifact|SpO2 artifact</EventConcept>
<Start>16343</Start>
<Duration>32</Duration>
<SignalLocation>SaO2</SignalLocation>
</ScoredEvent>
<ScoredEvent>
<EventType>Respiratory|Respiratory</EventType>
<EventConcept>SpO2 artifact|SpO2 artifact</EventConcept>
<Start>16388</Start>
<Duration>30</Duration>
<SignalLocation>SaO2</SignalLocation>
</ScoredEvent>
<ScoredEvent>
<EventType>Arousals|Arousals</EventType>
<EventConcept>Arousal resulting from respiratory effort|Arousal (RESP ARO)</EventConcept>
<Start>16416.8</Start>
<Duration>23.2</Duration>
<SignalLocation>C3</SignalLocation>
</ScoredEvent>
<ScoredEvent>
<EventType>Respiratory|Respiratory</EventType>
<EventConcept>SpO2 artifact|SpO2 artifact</EventConcept>
<Start>16431</Start>
<Duration>15</Duration>
<SignalLocation>SaO2</SignalLocation>
</ScoredEvent>
<ScoredEvent>
<EventType>Respiratory|Respiratory</EventType>
<EventConcept>SpO2 artifact|SpO2 artifact</EventConcept>
<Start>16466</Start>
<Duration>32</Duration>
<SignalLocation>SaO2</SignalLocation>
</ScoredEvent>
<ScoredEvent>
<EventType>Respiratory|Respiratory</EventType>
<EventConcept>SpO2 artifact|SpO2 artifact</EventConcept>
<Start>16508</Start>
<Duration>5</Duration>
<SignalLocation>SaO2</SignalLocation>
</ScoredEvent>
<ScoredEvent>
<EventType>Respiratory|Respiratory</EventType>
<EventConcept>SpO2 artifact|SpO2 artifact</EventConcept>
<Start>16548</Start>
<Duration>6</Duration>
<SignalLocation>SaO2</SignalLocation>
</ScoredEvent>
<ScoredEvent>
<EventType>Respiratory|Respiratory</EventType>
<EventConcept>SpO2 artifact|SpO2 artifact</EventConcept>
<Start>16566</Start>
<Duration>11</Duration>
<SignalLocation>SaO2</SignalLocation>
</ScoredEvent>
<ScoredEvent>
<EventType>Respiratory|Respiratory</EventType>
<EventConcept>SpO2 artifact|SpO2 artifact</EventConcept>
<Start>16590</Start>
<Duration>37</Duration>
<SignalLocation>SaO2</SignalLocation>
</ScoredEvent>
<ScoredEvent>
<EventType>Respiratory|Respiratory</EventType>
<EventConcept>SpO2 artifact|SpO2 artifact</EventConcept>
<Start>16638</Start>
<Duration>6</Duration>
<SignalLocation>SaO2</SignalLocation>
</ScoredEvent>
<ScoredEvent>
<EventType>Respiratory|Respiratory</EventType>
<EventConcept>SpO2 artifact|SpO2 artifact</EventConcept>
<Start>16654</Start>
<Duration>58</Duration>
<SignalLocation>SaO2</SignalLocation>
</ScoredEvent>
<ScoredEvent>
<EventType>Respiratory|Respiratory</EventType>
<EventConcept>SpO2 artifact|SpO2 artifact</EventConcept>
<Start>16733</Start>
<Duration>6</Duration>
<SignalLocation>SaO2</SignalLocation>
</ScoredEvent>
<ScoredEvent>
<EventType>Respiratory|Respiratory</EventType>
<EventConcept>SpO2 artifact|SpO2 artifact</EventConcept>
<Start>16759</Start>
<Duration>9</Duration>
<SignalLocation>SaO2</SignalLocation>
</ScoredEvent>
<ScoredEvent>
<EventType>Respiratory|Respiratory</EventType>
<EventConcept>SpO2 artifact|SpO2 artifact</EventConcept>
<Start>16826</Start>
<Duration>17</Duration>
<SignalLocation>SaO2</SignalLocation>
</ScoredEvent>
<ScoredEvent>
<EventType>Respiratory|Respiratory</EventType>
<EventConcept>SpO2 artifact|SpO2 artifact</EventConcept>
<Start>16885</Start>
<Duration>40</Duration>
<SignalLocation>SaO2</SignalLocation>
</ScoredEvent>
<ScoredEvent>
<EventType>Limb Movement|Limb Movement</EventType>
<EventConcept>Limb movement - left|Limb Movement (Left)</EventConcept>
<Start>16933.8</Start>
<Duration>9.4</Duration>
<SignalLocation>L Leg</SignalLocation>
</ScoredEvent>
<ScoredEvent>
<EventType>Respiratory|Respiratory</EventType>
<EventConcept>SpO2 artifact|SpO2 artifact</EventConcept>
<Start>16955.1</Start>
<Duration>671.5</Duration>
<SignalLocation>SaO2</SignalLocation>
</ScoredEvent>
<ScoredEvent>
<EventType>Limb Movement|Limb Movement</EventType>
<EventConcept>Limb movement - left|Limb Movement (Left)</EventConcept>
<Start>16971.4</Start>
<Duration>0.7</Duration>
<SignalLocation>L Leg</SignalLocation>
</ScoredEvent>
<ScoredEvent>
<EventType>Limb Movement|Limb Movement</EventType>
<EventConcept>Limb movement - left|Limb Movement (Left)</EventConcept>
<Start>17006.4</Start>
<Duration>1.5</Duration>
<SignalLocation>L Leg</SignalLocation>
</ScoredEvent>
<ScoredEvent>
<EventType>Limb Movement|Limb Movement</EventType>
<EventConcept>Limb movement - left|Limb Movement (Left)</EventConcept>
<Start>17051.3</Start>
<Duration>5.4</Duration>
<SignalLocation>L Leg</SignalLocation>
</ScoredEvent>
<ScoredEvent>
<EventType>Arousals|Arousals</EventType>
<EventConcept>Arousal resulting from respiratory effort|Arousal (RESP ARO)</EventConcept>
<Start>17073.3</Start>
<Duration>19.1</Duration>
<SignalLocation>C3</SignalLocation>
</ScoredEvent>
<ScoredEvent>
<EventType>Respiratory|Respiratory</EventType>
<EventConcept>Hypopnea|Hypopnea</EventConcept>
<Start>17257</Start>
<Duration>23.6</Duration>
<SignalLocation>ABDO EFFORT</SignalLocation>
</ScoredEvent>
<ScoredEvent>
<EventType>Arousals|Arousals</EventType>
<EventConcept>Arousal resulting from respiratory effort|Arousal (RESP ARO)</EventConcept>
<Start>17281.7</Start>
<Duration>11.3</Duration>
<SignalLocation>C3</SignalLocation>
</ScoredEvent>
<ScoredEvent>
<EventType>Arousals|Arousals</EventType>
<EventConcept>Arousal resulting from respiratory effort|Arousal (RESP ARO)</EventConcept>
<Start>17463.7</Start>
<Duration>17.8</Duration>
<SignalLocation>C3</SignalLocation>
</ScoredEvent>
<ScoredEvent>
<EventType>Limb Movement|Limb Movement</EventType>
<EventConcept>Limb movement - left|Limb Movement (Left)</EventConcept>
<Start>17514</Start>
<Duration>8</Duration>
<SignalLocation>L Leg</SignalLocation>
</ScoredEvent>
<ScoredEvent>
<EventType>Arousals|Arousals</EventType>
<EventConcept>Arousal resulting from respiratory effort|Arousal (RESP ARO)</EventConcept>
<Start>17520</Start>
<Duration>8.1</Duration>
<SignalLocation>C3</SignalLocation>
</ScoredEvent>
<ScoredEvent>
<EventType>Arousals|Arousals</EventType>
<EventConcept>Arousal resulting from respiratory effort|Arousal (RESP ARO)</EventConcept>
<Start>17583.1</Start>
<Duration>13.5</Duration>
<SignalLocation>C3</SignalLocation>
</ScoredEvent>
<ScoredEvent>
<EventType>Respiratory|Respiratory</EventType>
<EventConcept>Hypopnea|Hypopnea</EventConcept>
<Start>17624</Start>
<Duration>11.9</Duration>
<SignalLocation>ABDO EFFORT</SignalLocation>
</ScoredEvent>
<ScoredEvent>
<EventType>Respiratory|Respiratory</EventType>
<EventConcept>SpO2 desaturation|SpO2 desaturation</EventConcept>
<Start>17654</Start>
<Duration>11.9</Duration>
<SignalLocation>SaO2</SignalLocation>
<SpO2Nadir>100</SpO2Nadir>
<SpO2Baseline>100.0</SpO2Baseline>
</ScoredEvent>
<ScoredEvent>
<EventType>Arousals|Arousals</EventType>
<EventConcept>Arousal resulting from respiratory effort|Arousal (RESP ARO)</EventConcept>
<Start>19083.2</Start>
<Duration>17.5</Duration>
<SignalLocation>C3</SignalLocation>
</ScoredEvent>
<ScoredEvent>
<EventType>Arousals|Arousals</EventType>
<EventConcept>Arousal resulting from respiratory effort|Arousal (RESP ARO)</EventConcept>
<Start>19132.1</Start>
<Duration>7.9</Duration>
<SignalLocation>C3</SignalLocation>
</ScoredEvent>
<ScoredEvent>
<EventType>Respiratory|Respiratory</EventType>
<EventConcept>Hypopnea|Hypopnea</EventConcept>
<Start>19146.4</Start>
<Duration>18.2</Duration>
<SignalLocation>ABDO EFFORT</SignalLocation>
</ScoredEvent>
<ScoredEvent>
<EventType>Respiratory|Respiratory</EventType>
<EventConcept>Hypopnea|Hypopnea</EventConcept>
<Start>19173.7</Start>
<Duration>20.4</Duration>
<SignalLocation>ABDO EFFORT</SignalLocation>
</ScoredEvent>
<ScoredEvent>
<EventType>Respiratory|Respiratory</EventType>
<EventConcept>SpO2 desaturation|SpO2 desaturation</EventConcept>
<Start>19176.4</Start>
<Duration>18.2</Duration>
<SignalLocation>SaO2</SignalLocation>
<SpO2Nadir>94</SpO2Nadir>
<SpO2Baseline>96.0</SpO2Baseline>
</ScoredEvent>
<ScoredEvent>
<EventType>Respiratory|Respiratory</EventType>
<EventConcept>SpO2 desaturation|SpO2 desaturation</EventConcept>
<Start>19203.7</Start>
<Duration>20.4</Duration>
<SignalLocation>SaO2</SignalLocation>
<SpO2Nadir>94</SpO2Nadir>
<SpO2Baseline>95.0</SpO2Baseline>
</ScoredEvent>
<ScoredEvent>
<EventType>Arousals|Arousals</EventType>
<EventConcept>Arousal resulting from respiratory effort|Arousal (RESP ARO)</EventConcept>
<Start>19283.7</Start>
<Duration>6.3</Duration>
<SignalLocation>C3</SignalLocation>
</ScoredEvent>
<ScoredEvent>
<EventType>Respiratory|Respiratory</EventType>
<EventConcept>SpO2 artifact|SpO2 artifact</EventConcept>
<Start>19299</Start>
<Duration>5</Duration>
<SignalLocation>SaO2</SignalLocation>
</ScoredEvent>
<ScoredEvent>
<EventType>Respiratory|Respiratory</EventType>
<EventConcept>SpO2 artifact|SpO2 artifact</EventConcept>
<Start>19771</Start>
<Duration>3</Duration>
<SignalLocation>SaO2</SignalLocation>
</ScoredEvent>
<ScoredEvent>
<EventType>Limb Movement|Limb Movement</EventType>
<EventConcept>Limb movement - left|Limb Movement (Left)</EventConcept>
<Start>20013</Start>
<Duration>6.1</Duration>
<SignalLocation>L Leg</SignalLocation>
</ScoredEvent>
<ScoredEvent>
<EventType>Limb Movement|Limb Movement</EventType>
<EventConcept>Limb movement - left|Limb Movement (Left)</EventConcept>
<Start>20040.5</Start>
<Duration>1.4</Duration>
<SignalLocation>L Leg</SignalLocation>
</ScoredEvent>
<ScoredEvent>
<EventType>Limb Movement|Limb Movement</EventType>
<EventConcept>Limb movement - left|Limb Movement (Left)</EventConcept>
<Start>20063.4</Start>
<Duration>1.6</Duration>
<SignalLocation>L Leg</SignalLocation>
</ScoredEvent>
<ScoredEvent>
<EventType>Limb Movement|Limb Movement</EventType>
<EventConcept>Limb movement - left|Limb Movement (Left)</EventConcept>
<Start>20089.8</Start>
<Duration>2.4</Duration>
<SignalLocation>L Leg</SignalLocation>
</ScoredEvent>
<ScoredEvent>
<EventType>Arousals|Arousals</EventType>
<EventConcept>Arousal resulting from respiratory effort|Arousal (RESP ARO)</EventConcept>
<Start>20354.9</Start>
<Duration>15.1</Duration>
<SignalLocation>C3</SignalLocation>
</ScoredEvent>
<ScoredEvent>
<EventType>Respiratory|Respiratory</EventType>
<EventConcept>Obstructive apnea|Obstructive Apnea</EventConcept>
<Start>20372.8</Start>
<Duration>31.5</Duration>
<SignalLocation>ABDO EFFORT</SignalLocation>
</ScoredEvent>
<ScoredEvent>
<EventType>Respiratory|Respiratory</EventType>
<EventConcept>SpO2 desaturation|SpO2 desaturation</EventConcept>
<Start>20402.8</Start>
<Duration>31.5</Duration>
<SignalLocation>SaO2</SignalLocation>
<SpO2Nadir>95</SpO2Nadir>
<SpO2Baseline>99.0</SpO2Baseline>
</ScoredEvent>
<ScoredEvent>
<EventType>Respiratory|Respiratory</EventType>
<EventConcept>Hypopnea|Hypopnea</EventConcept>
<Start>20492</Start>
<Duration>16.8</Duration>
<SignalLocation>ABDO EFFORT</SignalLocation>
</ScoredEvent>
<ScoredEvent>
<EventType>Respiratory|Respiratory</EventType>
<EventConcept>SpO2 desaturation|SpO2 desaturation</EventConcept>
<Start>20522</Start>
<Duration>16.8</Duration>
<SignalLocation>SaO2</SignalLocation>
<SpO2Nadir>94</SpO2Nadir>
<SpO2Baseline>96.0</SpO2Baseline>
</ScoredEvent>
<ScoredEvent>
<EventType>Arousals|Arousals</EventType>
<EventConcept>Arousal resulting from respiratory effort|Arousal (RESP ARO)</EventConcept>
<Start>22237</Start>
<Duration>15.2</Duration>
<SignalLocation>C3</SignalLocation>
</ScoredEvent>
<ScoredEvent>
<EventType>Arousals|Arousals</EventType>
<EventConcept>Arousal resulting from respiratory effort|Arousal (RESP ARO)</EventConcept>
<Start>22279.2</Start>
<Duration>10.8</Duration>
<SignalLocation>C3</SignalLocation>
</ScoredEvent>
<ScoredEvent>
<EventType>Limb Movement|Limb Movement</EventType>
<EventConcept>Limb movement - left|Limb Movement (Left)</EventConcept>
<Start>22281.2</Start>
<Duration>32.7</Duration>
<SignalLocation>L Leg</SignalLocation>
</ScoredEvent>
<ScoredEvent>
<EventType>Respiratory|Respiratory</EventType>
<EventConcept>SpO2 artifact|SpO2 artifact</EventConcept>
<Start>22302</Start>
<Duration>17</Duration>
<SignalLocation>SaO2</SignalLocation>
</ScoredEvent>
<ScoredEvent>
<EventType>Limb Movement|Limb Movement</EventType>
<EventConcept>Limb movement - left|Limb Movement (Left)</EventConcept>
<Start>22481.3</Start>
<Duration>7</Duration>
<SignalLocation>L Leg</SignalLocation>
</ScoredEvent>
<ScoredEvent>
<EventType>Respiratory|Respiratory</EventType>
<EventConcept>Hypopnea|Hypopnea</EventConcept>
<Start>22494.7</Start>
<Duration>18.1</Duration>
<SignalLocation>ABDO EFFORT</SignalLocation>
</ScoredEvent>
<ScoredEvent>
<EventType>Respiratory|Respiratory</EventType>
<EventConcept>SpO2 desaturation|SpO2 desaturation</EventConcept>
<Start>22524.7</Start>
<Duration>18.1</Duration>
<SignalLocation>SaO2</SignalLocation>
<SpO2Nadir>95</SpO2Nadir>
<SpO2Baseline>96.0</SpO2Baseline>
</ScoredEvent>
<ScoredEvent>
<EventType>Arousals|Arousals</EventType>
<EventConcept>Arousal resulting from respiratory effort|Arousal (RESP ARO)</EventConcept>
<Start>23108.9</Start>
<Duration>21.1</Duration>
<SignalLocation>C3</SignalLocation>
</ScoredEvent>
<ScoredEvent>
<EventType>Arousals|Arousals</EventType>
<EventConcept>Arousal resulting from respiratory effort|Arousal (RESP ARO)</EventConcept>
<Start>23173.3</Start>
<Duration>9.3</Duration>
<SignalLocation>C3</SignalLocation>
</ScoredEvent>
<ScoredEvent>
<EventType>Arousals|Arousals</EventType>
<EventConcept>Arousal resulting from respiratory effort|Arousal (RESP ARO)</EventConcept>
<Start>23267.5</Start>
<Duration>5.1</Duration>
<SignalLocation>C3</SignalLocation>
</ScoredEvent>
<ScoredEvent>
<EventType>Respiratory|Respiratory</EventType>
<EventConcept>SpO2 artifact|SpO2 artifact</EventConcept>
<Start>24178</Start>
<Duration>4</Duration>
<SignalLocation>SaO2</SignalLocation>
</ScoredEvent>
<ScoredEvent>
<EventType>Respiratory|Respiratory</EventType>
<EventConcept>Hypopnea|Hypopnea</EventConcept>
<Start>24275.1</Start>
<Duration>19.8</Duration>
<SignalLocation>ABDO EFFORT</SignalLocation>
</ScoredEvent>
<ScoredEvent>
<EventType>Respiratory|Respiratory</EventType>
<EventConcept>SpO2 desaturation|SpO2 desaturation</EventConcept>
<Start>24305.1</Start>
<Duration>19.8</Duration>
<SignalLocation>SaO2</SignalLocation>
<SpO2Nadir>96</SpO2Nadir>
<SpO2Baseline>97.0</SpO2Baseline>
</ScoredEvent>
<ScoredEvent>
<EventType>Arousals|Arousals</EventType>
<EventConcept>Arousal resulting from respiratory effort|Arousal (RESP ARO)</EventConcept>
<Start>24320.1</Start>
<Duration>9.9</Duration>
<SignalLocation>C3</SignalLocation>
</ScoredEvent>
<ScoredEvent>
<EventType>Respiratory|Respiratory</EventType>
<EventConcept>SpO2 artifact|SpO2 artifact</EventConcept>
<Start>24329</Start>
<Duration>11</Duration>
<SignalLocation>SaO2</SignalLocation>
</ScoredEvent>
<ScoredEvent>
<EventType>Respiratory|Respiratory</EventType>
<EventConcept>Hypopnea|Hypopnea</EventConcept>
<Start>24379.8</Start>
<Duration>23.6</Duration>
<SignalLocation>ABDO EFFORT</SignalLocation>
</ScoredEvent>
<ScoredEvent>
<EventType>Respiratory|Respiratory</EventType>
<EventConcept>SpO2 desaturation|SpO2 desaturation</EventConcept>
<Start>24409.8</Start>
<Duration>23.6</Duration>
<SignalLocation>SaO2</SignalLocation>
<SpO2Nadir>97</SpO2Nadir>
<SpO2Baseline>98.0</SpO2Baseline>
</ScoredEvent>
<ScoredEvent>
<EventType>Arousals|Arousals</EventType>
<EventConcept>Arousal resulting from respiratory effort|Arousal (RESP ARO)</EventConcept>
<Start>24893.4</Start>
<Duration>6.6</Duration>
<SignalLocation>C3</SignalLocation>
</ScoredEvent>
<ScoredEvent>
<EventType>Arousals|Arousals</EventType>
<EventConcept>Arousal resulting from respiratory effort|Arousal (RESP ARO)</EventConcept>
<Start>24947.8</Start>
<Duration>12.2</Duration>
<SignalLocation>C3</SignalLocation>
</ScoredEvent>
<ScoredEvent>
<EventType>Respiratory|Respiratory</EventType>
<EventConcept>SpO2 artifact|SpO2 artifact</EventConcept>
<Start>24999</Start>
<Duration>10</Duration>
<SignalLocation>SaO2</SignalLocation>
</ScoredEvent>
<ScoredEvent>
<EventType>Arousals|Arousals</EventType>
<EventConcept>Arousal resulting from respiratory effort|Arousal (RESP ARO)</EventConcept>
<Start>25091.2</Start>
<Duration>9.7</Duration>
<SignalLocation>C3</SignalLocation>
</ScoredEvent>
<ScoredEvent>
<EventType>Respiratory|Respiratory</EventType>
<EventConcept>SpO2 artifact|SpO2 artifact</EventConcept>
<Start>25101</Start>
<Duration>5</Duration>
<SignalLocation>SaO2</SignalLocation>
</ScoredEvent>
<ScoredEvent>
<EventType>Respiratory|Respiratory</EventType>
<EventConcept>Hypopnea|Hypopnea</EventConcept>
<Start>25187.3</Start>
<Duration>15.6</Duration>
<SignalLocation>ABDO EFFORT</SignalLocation>
</ScoredEvent>
<ScoredEvent>
<EventType>Respiratory|Respiratory</EventType>
<EventConcept>SpO2 desaturation|SpO2 desaturation</EventConcept>
<Start>25217.3</Start>
<Duration>15.6</Duration>
<SignalLocation>SaO2</SignalLocation>
<SpO2Nadir>95</SpO2Nadir>
<SpO2Baseline>96.0</SpO2Baseline>
</ScoredEvent>
<ScoredEvent>
<EventType>Arousals|Arousals</EventType>
<EventConcept>Arousal resulting from respiratory effort|Arousal (RESP ARO)</EventConcept>
<Start>25913.5</Start>
<Duration>6.1</Duration>
<SignalLocation>C3</SignalLocation>
</ScoredEvent>
<ScoredEvent>
<EventType>Respiratory|Respiratory</EventType>
<EventConcept>SpO2 artifact|SpO2 artifact</EventConcept>
<Start>25941</Start>
<Duration>3</Duration>
<SignalLocation>SaO2</SignalLocation>
</ScoredEvent>
<ScoredEvent>
<EventType>Respiratory|Respiratory</EventType>
<EventConcept>Hypopnea|Hypopnea</EventConcept>
<Start>26297.3</Start>
<Duration>21</Duration>
<SignalLocation>ABDO EFFORT</SignalLocation>
</ScoredEvent>
<ScoredEvent>
<EventType>Arousals|Arousals</EventType>
<EventConcept>Arousal resulting from respiratory effort|Arousal (RESP ARO)</EventConcept>
<Start>26298.7</Start>
<Duration>11.3</Duration>
<SignalLocation>C3</SignalLocation>
</ScoredEvent>
<ScoredEvent>
<EventType>Respiratory|Respiratory</EventType>
<EventConcept>SpO2 desaturation|SpO2 desaturation</EventConcept>
<Start>26327.3</Start>
<Duration>21</Duration>
<SignalLocation>SaO2</SignalLocation>
<SpO2Nadir>93</SpO2Nadir>
<SpO2Baseline>97.0</SpO2Baseline>
</ScoredEvent>
<ScoredEvent>
<EventType>Respiratory|Respiratory</EventType>
<EventConcept>SpO2 artifact|SpO2 artifact</EventConcept>
<Start>26381</Start>
<Duration>11</Duration>
<SignalLocation>SaO2</SignalLocation>
</ScoredEvent>
<ScoredEvent>
<EventType>Respiratory|Respiratory</EventType>
<EventConcept>SpO2 artifact|SpO2 artifact</EventConcept>
<Start>26404</Start>
<Duration>7</Duration>
<SignalLocation>SaO2</SignalLocation>
</ScoredEvent>
<ScoredEvent>
<EventType>Arousals|Arousals</EventType>
<EventConcept>Arousal resulting from respiratory effort|Arousal (RESP ARO)</EventConcept>
<Start>26479.8</Start>
<Duration>7.5</Duration>
<SignalLocation>C3</SignalLocation>
</ScoredEvent>
<ScoredEvent>
<EventType>Respiratory|Respiratory</EventType>
<EventConcept>SpO2 artifact|SpO2 artifact</EventConcept>
<Start>26576</Start>
<Duration>46</Duration>
<SignalLocation>SaO2</SignalLocation>
</ScoredEvent>
<ScoredEvent>
<EventType>Respiratory|Respiratory</EventType>
<EventConcept>SpO2 artifact|SpO2 artifact</EventConcept>
<Start>26632</Start>
<Duration>22</Duration>
<SignalLocation>SaO2</SignalLocation>
</ScoredEvent>
<ScoredEvent>
<EventType>Respiratory|Respiratory</EventType>
<EventConcept>SpO2 artifact|SpO2 artifact</EventConcept>
<Start>26696</Start>
<Duration>6</Duration>
<SignalLocation>SaO2</SignalLocation>
</ScoredEvent>
<ScoredEvent>
<EventType>Respiratory|Respiratory</EventType>
<EventConcept>SpO2 artifact|SpO2 artifact</EventConcept>
<Start>26711</Start>
<Duration>54</Duration>
<SignalLocation>SaO2</SignalLocation>
</ScoredEvent>
<ScoredEvent>
<EventType>Respiratory|Respiratory</EventType>
<EventConcept>SpO2 artifact|SpO2 artifact</EventConcept>
<Start>26787</Start>
<Duration>25</Duration>
<SignalLocation>SaO2</SignalLocation>
</ScoredEvent>
<ScoredEvent>
<EventType>Respiratory|Respiratory</EventType>
<EventConcept>SpO2 artifact|SpO2 artifact</EventConcept>
<Start>26877</Start>
<Duration>31</Duration>
<SignalLocation>SaO2</SignalLocation>
</ScoredEvent>
<ScoredEvent>
<EventType>Limb Movement|Limb Movement</EventType>
<EventConcept>Limb movement - left|Limb Movement (Left)</EventConcept>
<Start>26920.8</Start>
<Duration>8.6</Duration>
<SignalLocation>L Leg</SignalLocation>
</ScoredEvent>
<ScoredEvent>
<EventType>Arousals|Arousals</EventType>
<EventConcept>Arousal resulting from respiratory effort|Arousal (RESP ARO)</EventConcept>
<Start>26925.2</Start>
<Duration>4.8</Duration>
<SignalLocation>C3</SignalLocation>
</ScoredEvent>
<ScoredEvent>
<EventType>Limb Movement|Limb Movement</EventType>
<EventConcept>Limb movement - left|Limb Movement (Left)</EventConcept>
<Start>26939.6</Start>
<Duration>12.6</Duration>
<SignalLocation>L Leg</SignalLocation>
</ScoredEvent>
<ScoredEvent>
<EventType>Respiratory|Respiratory</EventType>
<EventConcept>SpO2 artifact|SpO2 artifact</EventConcept>
<Start>26941</Start>
<Duration>12</Duration>
<SignalLocation>SaO2</SignalLocation>
</ScoredEvent>
<ScoredEvent>
<EventType>Arousals|Arousals</EventType>
<EventConcept>Arousal resulting from respiratory effort|Arousal (RESP ARO)</EventConcept>
<Start>26948.9</Start>
<Duration>5.6</Duration>
<SignalLocation>C3</SignalLocation>
</ScoredEvent>
<ScoredEvent>
<EventType>Limb Movement|Limb Movement</EventType>
<EventConcept>Limb movement - left|Limb Movement (Left)</EventConcept>
<Start>27031.8</Start>
<Duration>19.6</Duration>
<SignalLocation>L Leg</SignalLocation>
</ScoredEvent>
<ScoredEvent>
<EventType>Respiratory|Respiratory</EventType>
<EventConcept>SpO2 artifact|SpO2 artifact</EventConcept>
<Start>27033</Start>
<Duration>8</Duration>
<SignalLocation>SaO2</SignalLocation>
</ScoredEvent>
<ScoredEvent>
<EventType>Arousals|Arousals</EventType>
<EventConcept>Arousal resulting from respiratory effort|Arousal (RESP ARO)</EventConcept>
<Start>27036.5</Start>
<Duration>7.1</Duration>
<SignalLocation>C3</SignalLocation>
</ScoredEvent>
<ScoredEvent>
<EventType>Respiratory|Respiratory</EventType>
<EventConcept>SpO2 artifact|SpO2 artifact</EventConcept>
<Start>27111</Start>
<Duration>18</Duration>
<SignalLocation>SaO2</SignalLocation>
</ScoredEvent>
<ScoredEvent>
<EventType>Limb Movement|Limb Movement</EventType>
<EventConcept>Limb movement - left|Limb Movement (Left)</EventConcept>
<Start>27427.9</Start>
<Duration>2.2</Duration>
<SignalLocation>L Leg</SignalLocation>
</ScoredEvent>
<ScoredEvent>
<EventType>Arousals|Arousals</EventType>
<EventConcept>Arousal resulting from respiratory effort|Arousal (RESP ARO)</EventConcept>
<Start>27488.9</Start>
<Duration>10.5</Duration>
<SignalLocation>C3</SignalLocation>
</ScoredEvent>
<ScoredEvent>
<EventType>Limb Movement|Limb Movement</EventType>
<EventConcept>Limb movement - left|Limb Movement (Left)</EventConcept>
<Start>27494.5</Start>
<Duration>1.5</Duration>
<SignalLocation>L Leg</SignalLocation>
</ScoredEvent>
<ScoredEvent>
<EventType>Arousals|Arousals</EventType>
<EventConcept>Arousal resulting from respiratory effort|Arousal (RESP ARO)</EventConcept>
<Start>27556.7</Start>
<Duration>10.4</Duration>
<SignalLocation>C3</SignalLocation>
</ScoredEvent>
<ScoredEvent>
<EventType>Limb Movement|Limb Movement</EventType>
<EventConcept>Limb movement - left|Limb Movement (Left)</EventConcept>
<Start>27556.8</Start>
<Duration>9.5</Duration>
<SignalLocation>L Leg</SignalLocation>
</ScoredEvent>
<ScoredEvent>
<EventType>Respiratory|Respiratory</EventType>
<EventConcept>Hypopnea|Hypopnea</EventConcept>
<Start>27578.8</Start>
<Duration>17.3</Duration>
<SignalLocation>ABDO EFFORT</SignalLocation>
</ScoredEvent>
<ScoredEvent>
<EventType>Respiratory|Respiratory</EventType>
<EventConcept>Hypopnea|Hypopnea</EventConcept>
<Start>27608.6</Start>
<Duration>20.4</Duration>
<SignalLocation>ABDO EFFORT</SignalLocation>
</ScoredEvent>
<ScoredEvent>
<EventType>Respiratory|Respiratory</EventType>
<EventConcept>SpO2 desaturation|SpO2 desaturation</EventConcept>
<Start>27608.8</Start>
<Duration>17.3</Duration>
<SignalLocation>SaO2</SignalLocation>
<SpO2Nadir>94</SpO2Nadir>
<SpO2Baseline>98.0</SpO2Baseline>
</ScoredEvent>
<ScoredEvent>
<EventType>Arousals|Arousals</EventType>
<EventConcept>Arousal resulting from respiratory effort|Arousal (RESP ARO)</EventConcept>
<Start>27635.3</Start>
<Duration>9.1</Duration>
<SignalLocation>C3</SignalLocation>
</ScoredEvent>
<ScoredEvent>
<EventType>Respiratory|Respiratory</EventType>
<EventConcept>SpO2 desaturation|SpO2 desaturation</EventConcept>
<Start>27638.6</Start>
<Duration>20.4</Duration>
<SignalLocation>SaO2</SignalLocation>
<SpO2Nadir>95</SpO2Nadir>
<SpO2Baseline>96.0</SpO2Baseline>
</ScoredEvent>
<ScoredEvent>
<EventType>Limb Movement|Limb Movement</EventType>
<EventConcept>Limb movement - left|Limb Movement (Left)</EventConcept>
<Start>27641.5</Start>
<Duration>2.2</Duration>
<SignalLocation>L Leg</SignalLocation>
</ScoredEvent>
<ScoredEvent>
<EventType>Limb Movement|Limb Movement</EventType>
<EventConcept>Limb movement - left|Limb Movement (Left)</EventConcept>
<Start>27888.5</Start>
<Duration>9.4</Duration>
<SignalLocation>L Leg</SignalLocation>
</ScoredEvent>
<ScoredEvent>
<EventType>Limb Movement|Limb Movement</EventType>
<EventConcept>Limb movement - left|Limb Movement (Left)</EventConcept>
<Start>27937.1</Start>
<Duration>2</Duration>
<SignalLocation>L Leg</SignalLocation>
</ScoredEvent>
<ScoredEvent>
<EventType>Limb Movement|Limb Movement</EventType>
<EventConcept>Limb movement - left|Limb Movement (Left)</EventConcept>
<Start>27969.2</Start>
<Duration>6.7</Duration>
<SignalLocation>L Leg</SignalLocation>
</ScoredEvent>
<ScoredEvent>
<EventType>Limb Movement|Limb Movement</EventType>
<EventConcept>Limb movement - left|Limb Movement (Left)</EventConcept>
<Start>27987.7</Start>
<Duration>1.4</Duration>
<SignalLocation>L Leg</SignalLocation>
</ScoredEvent>
<ScoredEvent>
<EventType>Arousals|Arousals</EventType>
<EventConcept>Arousal resulting from respiratory effort|Arousal (RESP ARO)</EventConcept>
<Start>29142.6</Start>
<Duration>17.4</Duration>
<SignalLocation>C3</SignalLocation>
</ScoredEvent>
<ScoredEvent>
<EventType>Respiratory|Respiratory</EventType>
<EventConcept>SpO2 artifact|SpO2 artifact</EventConcept>
<Start>29174</Start>
<Duration>11</Duration>
<SignalLocation>SaO2</SignalLocation>
</ScoredEvent>
<ScoredEvent>
<EventType>Respiratory|Respiratory</EventType>
<EventConcept>SpO2 artifact|SpO2 artifact</EventConcept>
<Start>29195</Start>
<Duration>3</Duration>
<SignalLocation>SaO2</SignalLocation>
</ScoredEvent>
<ScoredEvent>
<EventType>Respiratory|Respiratory</EventType>
<EventConcept>Hypopnea|Hypopnea</EventConcept>
<Start>29286.2</Start>
<Duration>20.5</Duration>
<SignalLocation>ABDO EFFORT</SignalLocation>
</ScoredEvent>
<ScoredEvent>
<EventType>Respiratory|Respiratory</EventType>
<EventConcept>SpO2 desaturation|SpO2 desaturation</EventConcept>
<Start>29316.2</Start>
<Duration>20.5</Duration>
<SignalLocation>SaO2</SignalLocation>
<SpO2Nadir>94</SpO2Nadir>
<SpO2Baseline>96.0</SpO2Baseline>
</ScoredEvent>
<ScoredEvent>
<EventType>Arousals|Arousals</EventType>
<EventConcept>Arousal resulting from respiratory effort|Arousal (RESP ARO)</EventConcept>
<Start>29340.6</Start>
<Duration>9.2</Duration>
<SignalLocation>C3</SignalLocation>
</ScoredEvent>
<ScoredEvent>
<EventType>Limb Movement|Limb Movement</EventType>
<EventConcept>Limb movement - left|Limb Movement (Left)</EventConcept>
<Start>29340.8</Start>
<Duration>7.8</Duration>
<SignalLocation>L Leg</SignalLocation>
</ScoredEvent>
<ScoredEvent>
<EventType>Respiratory|Respiratory</EventType>
<EventConcept>Hypopnea|Hypopnea</EventConcept>
<Start>29356.3</Start>
<Duration>19.9</Duration>
<SignalLocation>ABDO EFFORT</SignalLocation>
</ScoredEvent>
<ScoredEvent>
<EventType>Respiratory|Respiratory</EventType>
<EventConcept>SpO2 desaturation|SpO2 desaturation</EventConcept>
<Start>29386.3</Start>
<Duration>19.9</Duration>
<SignalLocation>SaO2</SignalLocation>
<SpO2Nadir>94</SpO2Nadir>
<SpO2Baseline>96.0</SpO2Baseline>
</ScoredEvent>
<ScoredEvent>
<EventType>Arousals|Arousals</EventType>
<EventConcept>Arousal resulting from respiratory effort|Arousal (RESP ARO)</EventConcept>
<Start>29420.7</Start>
<Duration>9.3</Duration>
<SignalLocation>C3</SignalLocation>
</ScoredEvent>
<ScoredEvent>
<EventType>Respiratory|Respiratory</EventType>
<EventConcept>Hypopnea|Hypopnea</EventConcept>
<Start>29451.8</Start>
<Duration>18.5</Duration>
<SignalLocation>ABDO EFFORT</SignalLocation>
</ScoredEvent>
<ScoredEvent>
<EventType>Respiratory|Respiratory</EventType>
<EventConcept>SpO2 desaturation|SpO2 desaturation</EventConcept>
<Start>29481.8</Start>
<Duration>18.5</Duration>
<SignalLocation>SaO2</SignalLocation>
<SpO2Nadir>93</SpO2Nadir>
<SpO2Baseline>95.0</SpO2Baseline>
</ScoredEvent>
<ScoredEvent>
<EventType>Arousals|Arousals</EventType>
<EventConcept>Arousal resulting from respiratory effort|Arousal (RESP ARO)</EventConcept>
<Start>29692.3</Start>
<Duration>19.6</Duration>
<SignalLocation>C3</SignalLocation>
</ScoredEvent>
<ScoredEvent>
<EventType>Arousals|Arousals</EventType>
<EventConcept>Arousal resulting from respiratory effort|Arousal (RESP ARO)</EventConcept>
<Start>29744.2</Start>
<Duration>13.8</Duration>
<SignalLocation>C3</SignalLocation>
</ScoredEvent>
<ScoredEvent>
<EventType>Limb Movement|Limb Movement</EventType>
<EventConcept>Limb movement - left|Limb Movement (Left)</EventConcept>
<Start>29745.2</Start>
<Duration>2.2</Duration>
<SignalLocation>L Leg</SignalLocation>
</ScoredEvent>
<ScoredEvent>
<EventType>Limb Movement|Limb Movement</EventType>
<EventConcept>Limb movement - left|Limb Movement (Left)</EventConcept>
<Start>29756</Start>
<Duration>3.3</Duration>
<SignalLocation>L Leg</SignalLocation>
</ScoredEvent>
<ScoredEvent>
<EventType>Arousals|Arousals</EventType>
<EventConcept>Arousal resulting from respiratory effort|Arousal (RESP ARO)</EventConcept>
<Start>29843.5</Start>
<Duration>14</Duration>
<SignalLocation>C3</SignalLocation>
</ScoredEvent>
<ScoredEvent>
<EventType>Limb Movement|Limb Movement</EventType>
<EventConcept>Limb movement - left|Limb Movement (Left)</EventConcept>
<Start>29852.4</Start>
<Duration>7.7</Duration>
<SignalLocation>L Leg</SignalLocation>
</ScoredEvent>
<ScoredEvent>
<EventType>Limb Movement|Limb Movement</EventType>
<EventConcept>Limb movement - left|Limb Movement (Left)</EventConcept>
<Start>29874</Start>
<Duration>2.5</Duration>
<SignalLocation>L Leg</SignalLocation>
</ScoredEvent>
<ScoredEvent>
<EventType>Limb Movement|Limb Movement</EventType>
<EventConcept>Limb movement - left|Limb Movement (Left)</EventConcept>
<Start>29889.2</Start>
<Duration>3.7</Duration>
<SignalLocation>L Leg</SignalLocation>
</ScoredEvent>
<ScoredEvent>
<EventType>Respiratory|Respiratory</EventType>
<EventConcept>SpO2 artifact|SpO2 artifact</EventConcept>
<Start>29902</Start>
<Duration>12</Duration>
<SignalLocation>SaO2</SignalLocation>
</ScoredEvent>
<ScoredEvent>
<EventType>Limb Movement|Limb Movement</EventType>
<EventConcept>Limb movement - left|Limb Movement (Left)</EventConcept>
<Start>29902.5</Start>
<Duration>6.4</Duration>
<SignalLocation>L Leg</SignalLocation>
</ScoredEvent>
<ScoredEvent>
<EventType>Limb Movement|Limb Movement</EventType>
<EventConcept>Limb movement - left|Limb Movement (Left)</EventConcept>
<Start>29915.6</Start>
<Duration>3</Duration>
<SignalLocation>L Leg</SignalLocation>
</ScoredEvent>
<ScoredEvent>
<EventType>Respiratory|Respiratory</EventType>
<EventConcept>Hypopnea|Hypopnea</EventConcept>
<Start>29924.1</Start>
<Duration>20.2</Duration>
<SignalLocation>ABDO EFFORT</SignalLocation>
</ScoredEvent>
<ScoredEvent>
<EventType>Respiratory|Respiratory</EventType>
<EventConcept>SpO2 artifact|SpO2 artifact</EventConcept>
<Start>29925</Start>
<Duration>39</Duration>
<SignalLocation>SaO2</SignalLocation>
</ScoredEvent>
<ScoredEvent>
<EventType>Arousals|Arousals</EventType>
<EventConcept>Arousal resulting from respiratory effort|Arousal (RESP ARO)</EventConcept>
<Start>29947.2</Start>
<Duration>22.7</Duration>
<SignalLocation>C3</SignalLocation>
</ScoredEvent>
<ScoredEvent>
<EventType>Arousals|Arousals</EventType>
<EventConcept>Arousal resulting from respiratory effort|Arousal (RESP ARO)</EventConcept>
<Start>30176.2</Start>
<Duration>18.8</Duration>
<SignalLocation>C3</SignalLocation>
</ScoredEvent>
<ScoredEvent>
<EventType>Respiratory|Respiratory</EventType>
<EventConcept>Hypopnea|Hypopnea</EventConcept>
<Start>30177.3</Start>
<Duration>16.7</Duration>
<SignalLocation>ABDO EFFORT</SignalLocation>
</ScoredEvent>
<ScoredEvent>
<EventType>Respiratory|Respiratory</EventType>
<EventConcept>SpO2 desaturation|SpO2 desaturation</EventConcept>
<Start>30207.3</Start>
<Duration>16.7</Duration>
<SignalLocation>SaO2</SignalLocation>
<SpO2Nadir>94</SpO2Nadir>
<SpO2Baseline>95.0</SpO2Baseline>
</ScoredEvent>
<ScoredEvent>
<EventType>Arousals|Arousals</EventType>
<EventConcept>Arousal resulting from respiratory effort|Arousal (RESP ARO)</EventConcept>
<Start>30393</Start>
<Duration>10.1</Duration>
<SignalLocation>C3</SignalLocation>
</ScoredEvent>
<ScoredEvent>
<EventType>Limb Movement|Limb Movement</EventType>
<EventConcept>Limb movement - left|Limb Movement (Left)</EventConcept>
<Start>30541.3</Start>
<Duration>3.7</Duration>
<SignalLocation>L Leg</SignalLocation>
</ScoredEvent>
<ScoredEvent>
<EventType>Arousals|Arousals</EventType>
<EventConcept>Arousal resulting from respiratory effort|Arousal (RESP ARO)</EventConcept>
<Start>30541.5</Start>
<Duration>9.6</Duration>
<SignalLocation>C3</SignalLocation>
</ScoredEvent>
<ScoredEvent>
<EventType>Respiratory|Respiratory</EventType>
<EventConcept>SpO2 artifact|SpO2 artifact</EventConcept>
<Start>30596</Start>
<Duration>11</Duration>
<SignalLocation>SaO2</SignalLocation>
</ScoredEvent>
<ScoredEvent>
<EventType>Limb Movement|Limb Movement</EventType>
<EventConcept>Limb movement - left|Limb Movement (Left)</EventConcept>
<Start>30603</Start>
<Duration>1.1</Duration>
<SignalLocation>L Leg</SignalLocation>
</ScoredEvent>
<ScoredEvent>
<EventType>Respiratory|Respiratory</EventType>
<EventConcept>Hypopnea|Hypopnea</EventConcept>
<Start>30614.9</Start>
<Duration>13.4</Duration>
<SignalLocation>ABDO EFFORT</SignalLocation>
</ScoredEvent>
<ScoredEvent>
<EventType>Respiratory|Respiratory</EventType>
<EventConcept>SpO2 desaturation|SpO2 desaturation</EventConcept>
<Start>30644.9</Start>
<Duration>13.4</Duration>
<SignalLocation>SaO2</SignalLocation>
<SpO2Nadir>93</SpO2Nadir>
<SpO2Baseline>95.0</SpO2Baseline>
</ScoredEvent>
<ScoredEvent>
<EventType>Limb Movement|Limb Movement</EventType>
<EventConcept>Limb movement - left|Limb Movement (Left)</EventConcept>
<Start>30651.9</Start>
<Duration>1.1</Duration>
<SignalLocation>L Leg</SignalLocation>
</ScoredEvent>
<ScoredEvent>
<EventType>Arousals|Arousals</EventType>
<EventConcept>Arousal resulting from respiratory effort|Arousal (RESP ARO)</EventConcept>
<Start>30670.8</Start>
<Duration>11.6</Duration>
<SignalLocation>C3</SignalLocation>
</ScoredEvent>
<ScoredEvent>
<EventType>Limb Movement|Limb Movement</EventType>
<EventConcept>Limb movement - left|Limb Movement (Left)</EventConcept>
<Start>30673</Start>
<Duration>6.9</Duration>
<SignalLocation>L Leg</SignalLocation>
</ScoredEvent>
<ScoredEvent>
<EventType>Respiratory|Respiratory</EventType>
<EventConcept>Hypopnea|Hypopnea</EventConcept>
<Start>30688.5</Start>
<Duration>17.3</Duration>
<SignalLocation>ABDO EFFORT</SignalLocation>
</ScoredEvent>
<ScoredEvent>
<EventType>Respiratory|Respiratory</EventType>
<EventConcept>SpO2 artifact|SpO2 artifact</EventConcept>
<Start>30689</Start>
<Duration>40</Duration>
<SignalLocation>SaO2</SignalLocation>
</ScoredEvent>
<ScoredEvent>
<EventType>Limb Movement|Limb Movement</EventType>
<EventConcept>Limb movement - left|Limb Movement (Left)</EventConcept>
<Start>30730.8</Start>
<Duration>0.7</Duration>
<SignalLocation>L Leg</SignalLocation>
</ScoredEvent>
<ScoredEvent>
<EventType>Respiratory|Respiratory</EventType>
<EventConcept>SpO2 artifact|SpO2 artifact</EventConcept>
<Start>30743</Start>
<Duration>27</Duration>
<SignalLocation>SaO2</SignalLocation>
</ScoredEvent>
<ScoredEvent>
<EventType>Arousals|Arousals</EventType>
<EventConcept>Arousal resulting from respiratory effort|Arousal (RESP ARO)</EventConcept>
<Start>30783.5</Start>
<Duration>26.5</Duration>
<SignalLocation>C3</SignalLocation>
</ScoredEvent>
<ScoredEvent>
<EventType>Respiratory|Respiratory</EventType>
<EventConcept>SpO2 artifact|SpO2 artifact</EventConcept>
<Start>30997</Start>
<Duration>7</Duration>
<SignalLocation>SaO2</SignalLocation>
</ScoredEvent>
<ScoredEvent>
<EventType>Respiratory|Respiratory</EventType>
<EventConcept>Hypopnea|Hypopnea</EventConcept>
<Start>31138</Start>
<Duration>14.8</Duration>
<SignalLocation>ABDO EFFORT</SignalLocation>
</ScoredEvent>
<ScoredEvent>
<EventType>Respiratory|Respiratory</EventType>
<EventConcept>SpO2 desaturation|SpO2 desaturation</EventConcept>
<Start>31168</Start>
<Duration>14.8</Duration>
<SignalLocation>SaO2</SignalLocation>
<SpO2Nadir>95</SpO2Nadir>
<SpO2Baseline>96.0</SpO2Baseline>
</ScoredEvent>
<ScoredEvent>
<EventType>Arousals|Arousals</EventType>
<EventConcept>Arousal resulting from respiratory effort|Arousal (RESP ARO)</EventConcept>
<Start>31233.6</Start>
<Duration>26.4</Duration>
<SignalLocation>C3</SignalLocation>
</ScoredEvent>
<ScoredEvent>
<EventType>Respiratory|Respiratory</EventType>
<EventConcept>Hypopnea|Hypopnea</EventConcept>
<Start>31308.3</Start>
<Duration>23.3</Duration>
<SignalLocation>ABDO EFFORT</SignalLocation>
</ScoredEvent>
<ScoredEvent>
<EventType>Respiratory|Respiratory</EventType>
<EventConcept>SpO2 desaturation|SpO2 desaturation</EventConcept>
<Start>31338.3</Start>
<Duration>23.3</Duration>
<SignalLocation>SaO2</SignalLocation>
<SpO2Nadir>94</SpO2Nadir>
<SpO2Baseline>96.0</SpO2Baseline>
</ScoredEvent>
<ScoredEvent>
<EventType>Arousals|Arousals</EventType>
<EventConcept>Arousal resulting from respiratory effort|Arousal (RESP ARO)</EventConcept>
<Start>31397.8</Start>
<Duration>9.2</Duration>
<SignalLocation>C3</SignalLocation>
</ScoredEvent>
<ScoredEvent>
<EventType>Respiratory|Respiratory</EventType>
<EventConcept>Hypopnea|Hypopnea</EventConcept>
<Start>31447</Start>
<Duration>21</Duration>
<SignalLocation>ABDO EFFORT</SignalLocation>
</ScoredEvent>
<ScoredEvent>
<EventType>Respiratory|Respiratory</EventType>
<EventConcept>SpO2 desaturation|SpO2 desaturation</EventConcept>
<Start>31477</Start>
<Duration>21</Duration>
<SignalLocation>SaO2</SignalLocation>
<SpO2Nadir>96</SpO2Nadir>
<SpO2Baseline>97.0</SpO2Baseline>
</ScoredEvent>
<ScoredEvent>
<EventType>Respiratory|Respiratory</EventType>
<EventConcept>Hypopnea|Hypopnea</EventConcept>
<Start>31563.3</Start>
<Duration>24.2</Duration>
<SignalLocation>ABDO EFFORT</SignalLocation>
</ScoredEvent>
<ScoredEvent>
<EventType>Respiratory|Respiratory</EventType>
<EventConcept>SpO2 desaturation|SpO2 desaturation</EventConcept>
<Start>31593.3</Start>
<Duration>24.2</Duration>
<SignalLocation>SaO2</SignalLocation>
<SpO2Nadir>93</SpO2Nadir>
<SpO2Baseline>96.0</SpO2Baseline>
</ScoredEvent>
<ScoredEvent>
<EventType>Arousals|Arousals</EventType>
<EventConcept>Arousal resulting from respiratory effort|Arousal (RESP ARO)</EventConcept>
<Start>31599.5</Start>
<Duration>12.3</Duration>
<SignalLocation>C3</SignalLocation>
</ScoredEvent>
<ScoredEvent>
<EventType>Respiratory|Respiratory</EventType>
<EventConcept>Hypopnea|Hypopnea</EventConcept>
<Start>31695.6</Start>
<Duration>15.9</Duration>
<SignalLocation>ABDO EFFORT</SignalLocation>
</ScoredEvent>
<ScoredEvent>
<EventType>Respiratory|Respiratory</EventType>
<EventConcept>SpO2 desaturation|SpO2 desaturation</EventConcept>
<Start>31725.6</Start>
<Duration>15.9</Duration>
<SignalLocation>SaO2</SignalLocation>
<SpO2Nadir>95</SpO2Nadir>
<SpO2Baseline>97.0</SpO2Baseline>
</ScoredEvent>
<ScoredEvent>
<EventType>Limb Movement|Limb Movement</EventType>
<EventConcept>Limb movement - left|Limb Movement (Left)</EventConcept>
<Start>31889.5</Start>
<Duration>4.2</Duration>
<SignalLocation>L Leg</SignalLocation>
</ScoredEvent>
<ScoredEvent>
<EventType>Arousals|Arousals</EventType>
<EventConcept>Arousal resulting from respiratory effort|Arousal (RESP ARO)</EventConcept>
<Start>31891.9</Start>
<Duration>18.7</Duration>
<SignalLocation>C3</SignalLocation>
</ScoredEvent>
<ScoredEvent>
<EventType>Respiratory|Respiratory</EventType>
<EventConcept>Hypopnea|Hypopnea</EventConcept>
<Start>31916.7</Start>
<Duration>19.9</Duration>
<SignalLocation>ABDO EFFORT</SignalLocation>
</ScoredEvent>
<ScoredEvent>
<EventType>Limb Movement|Limb Movement</EventType>
<EventConcept>Limb movement - left|Limb Movement (Left)</EventConcept>
<Start>31934.6</Start>
<Duration>8.2</Duration>
<SignalLocation>L Leg</SignalLocation>
</ScoredEvent>
<ScoredEvent>
<EventType>Arousals|Arousals</EventType>
<EventConcept>Arousal resulting from respiratory effort|Arousal (RESP ARO)</EventConcept>
<Start>31938.3</Start>
<Duration>8</Duration>
<SignalLocation>C3</SignalLocation>
</ScoredEvent>
<ScoredEvent>
<EventType>Respiratory|Respiratory</EventType>
<EventConcept>Hypopnea|Hypopnea</EventConcept>
<Start>31953.6</Start>
<Duration>29.8</Duration>
<SignalLocation>ABDO EFFORT</SignalLocation>
</ScoredEvent>
<ScoredEvent>
<EventType>Arousals|Arousals</EventType>
<EventConcept>Arousal resulting from respiratory effort|Arousal (RESP ARO)</EventConcept>
<Start>31984.6</Start>
<Duration>20</Duration>
<SignalLocation>C3</SignalLocation>
</ScoredEvent>
<ScoredEvent>
<EventType>Limb Movement|Limb Movement</EventType>
<EventConcept>Limb movement - left|Limb Movement (Left)</EventConcept>
<Start>32090.8</Start>
<Duration>0.8</Duration>
<SignalLocation>L Leg</SignalLocation>
</ScoredEvent>
<ScoredEvent>
<EventType>Limb Movement|Limb Movement</EventType>
<EventConcept>Limb movement - left|Limb Movement (Left)</EventConcept>
<Start>32130.7</Start>
<Duration>2</Duration>
<SignalLocation>L Leg</SignalLocation>
</ScoredEvent>
<ScoredEvent>
<EventType>Limb Movement|Limb Movement</EventType>
<EventConcept>Limb movement - left|Limb Movement (Left)</EventConcept>
<Start>32154.1</Start>
<Duration>4.1</Duration>
<SignalLocation>L Leg</SignalLocation>
</ScoredEvent>
<ScoredEvent>
<EventType>Limb Movement|Limb Movement</EventType>
<EventConcept>Limb movement - left|Limb Movement (Left)</EventConcept>
<Start>32188.8</Start>
<Duration>9.1</Duration>
<SignalLocation>L Leg</SignalLocation>
</ScoredEvent>
<ScoredEvent>
<EventType>Respiratory|Respiratory</EventType>
<EventConcept>SpO2 artifact|SpO2 artifact</EventConcept>
<Start>32204</Start>
<Duration>14</Duration>
<SignalLocation>SaO2</SignalLocation>
</ScoredEvent>
<ScoredEvent>
<EventType>Limb Movement|Limb Movement</EventType>
<EventConcept>Limb movement - left|Limb Movement (Left)</EventConcept>
<Start>32214.7</Start>
<Duration>4.4</Duration>
<SignalLocation>L Leg</SignalLocation>
</ScoredEvent>
<ScoredEvent>
<EventType>Arousals|Arousals</EventType>
<EventConcept>Arousal resulting from respiratory effort|Arousal (RESP ARO)</EventConcept>
<Start>32326.2</Start>
<Duration>8.9</Duration>
<SignalLocation>C3</SignalLocation>
</ScoredEvent>
<ScoredEvent>
<EventType>Limb Movement|Limb Movement</EventType>
<EventConcept>Limb movement - left|Limb Movement (Left)</EventConcept>
<Start>32328.9</Start>
<Duration>3.7</Duration>
<SignalLocation>L Leg</SignalLocation>
</ScoredEvent>
<ScoredEvent>
<EventType>Respiratory|Respiratory</EventType>
<EventConcept>SpO2 artifact|SpO2 artifact</EventConcept>
<Start>32334</Start>
<Duration>15</Duration>
<SignalLocation>SaO2</SignalLocation>
</ScoredEvent>
<ScoredEvent>
<EventType>Respiratory|Respiratory</EventType>
<EventConcept>Hypopnea|Hypopnea</EventConcept>
<Start>32339.5</Start>
<Duration>35.1</Duration>
<SignalLocation>ABDO EFFORT</SignalLocation>
</ScoredEvent>
<ScoredEvent>
<EventType>Limb Movement|Limb Movement</EventType>
<EventConcept>Limb movement - left|Limb Movement (Left)</EventConcept>
<Start>32365.9</Start>
<Duration>1.7</Duration>
<SignalLocation>L Leg</SignalLocation>
</ScoredEvent>
<ScoredEvent>
<EventType>Limb Movement|Limb Movement</EventType>
<EventConcept>Limb movement - left|Limb Movement (Left)</EventConcept>
<Start>32388.9</Start>
<Duration>12.2</Duration>
<SignalLocation>L Leg</SignalLocation>
</ScoredEvent>
<ScoredEvent>
<EventType>Respiratory|Respiratory</EventType>
<EventConcept>Hypopnea|Hypopnea</EventConcept>
<Start>32395.9</Start>
<Duration>34.7</Duration>
<SignalLocation>ABDO EFFORT</SignalLocation>
</ScoredEvent>
<ScoredEvent>
<EventType>Limb Movement|Limb Movement</EventType>
<EventConcept>Limb movement - left|Limb Movement (Left)</EventConcept>
<Start>32429.4</Start>
<Duration>4.1</Duration>
<SignalLocation>L Leg</SignalLocation>
</ScoredEvent>
<ScoredEvent>
<EventType>Arousals|Arousals</EventType>
<EventConcept>Arousal resulting from respiratory effort|Arousal (RESP ARO)</EventConcept>
<Start>32430.5</Start>
<Duration>7.2</Duration>
<SignalLocation>C3</SignalLocation>
</ScoredEvent>
<ScoredEvent>
<EventType>Limb Movement|Limb Movement</EventType>
<EventConcept>Limb movement - left|Limb Movement (Left)</EventConcept>
<Start>32446.7</Start>
<Duration>2.6</Duration>
<SignalLocation>L Leg</SignalLocation>
</ScoredEvent>
<ScoredEvent>
<EventType>Respiratory|Respiratory</EventType>
<EventConcept>Hypopnea|Hypopnea</EventConcept>
<Start>32455.8</Start>
<Duration>25.8</Duration>
<SignalLocation>ABDO EFFORT</SignalLocation>
</ScoredEvent>
<ScoredEvent>
<EventType>Limb Movement|Limb Movement</EventType>
<EventConcept>Limb movement - left|Limb Movement (Left)</EventConcept>
<Start>32482.1</Start>
<Duration>3.9</Duration>
<SignalLocation>L Leg</SignalLocation>
</ScoredEvent>
<ScoredEvent>
<EventType>Arousals|Arousals</EventType>
<EventConcept>Arousal resulting from respiratory effort|Arousal (RESP ARO)</EventConcept>
<Start>32488.3</Start>
<Duration>7.6</Duration>
<SignalLocation>C3</SignalLocation>
</ScoredEvent>
<ScoredEvent>
<EventType>Arousals|Arousals</EventType>
<EventConcept>Arousal resulting from respiratory effort|Arousal (RESP ARO)</EventConcept>
<Start>32529.1</Start>
<Duration>20.9</Duration>
<SignalLocation>C3</SignalLocation>
</ScoredEvent>
<ScoredEvent>
<EventType>Arousals|Arousals</EventType>
<EventConcept>Arousal resulting from respiratory effort|Arousal (RESP ARO)</EventConcept>
<Start>32619.2</Start>
<Duration>7.4</Duration>
<SignalLocation>C3</SignalLocation>
</ScoredEvent>
<ScoredEvent>
<EventType>Arousals|Arousals</EventType>
<EventConcept>Arousal resulting from respiratory effort|Arousal (RESP ARO)</EventConcept>
<Start>32662.5</Start>
<Duration>7.5</Duration>
<SignalLocation>C3</SignalLocation>
</ScoredEvent>
<ScoredEvent>
<EventType>Respiratory|Respiratory</EventType>
<EventConcept>Hypopnea|Hypopnea</EventConcept>
<Start>32702.2</Start>
<Duration>32.9</Duration>
<SignalLocation>ABDO EFFORT</SignalLocation>
</ScoredEvent>
<ScoredEvent>
<EventType>Respiratory|Respiratory</EventType>
<EventConcept>Hypopnea|Hypopnea</EventConcept>
<Start>32814</Start>
<Duration>20.7</Duration>
<SignalLocation>ABDO EFFORT</SignalLocation>
</ScoredEvent>
<ScoredEvent>
<EventType>Respiratory|Respiratory</EventType>
<EventConcept>Hypopnea|Hypopnea</EventConcept>
<Start>32878.9</Start>
<Duration>32.3</Duration>
<SignalLocation>ABDO EFFORT</SignalLocation>
</ScoredEvent>
<ScoredEvent>
<EventType>Arousals|Arousals</EventType>
<EventConcept>Arousal resulting from respiratory effort|Arousal (RESP ARO)</EventConcept>
<Start>32928.2</Start>
<Duration>11.6</Duration>
<SignalLocation>C3</SignalLocation>
</ScoredEvent>
<ScoredEvent>
<EventType>Respiratory|Respiratory</EventType>
<EventConcept>SpO2 artifact|SpO2 artifact</EventConcept>
<Start>32932</Start>
<Duration>4</Duration>
<SignalLocation>SaO2</SignalLocation>
</ScoredEvent>
<ScoredEvent>
<EventType>Respiratory|Respiratory</EventType>
<EventConcept>SpO2 artifact|SpO2 artifact</EventConcept>
<Start>32961</Start>
<Duration>24</Duration>
<SignalLocation>SaO2</SignalLocation>
</ScoredEvent>
<ScoredEvent>
<EventType>Respiratory|Respiratory</EventType>
<EventConcept>SpO2 artifact|SpO2 artifact</EventConcept>
<Start>32995</Start>
<Duration>3</Duration>
<SignalLocation>SaO2</SignalLocation>
</ScoredEvent>
<ScoredEvent>
<EventType>Respiratory|Respiratory</EventType>
<EventConcept>SpO2 artifact|SpO2 artifact</EventConcept>
<Start>33014</Start>
<Duration>15</Duration>
<SignalLocation>SaO2</SignalLocation>
</ScoredEvent>
<ScoredEvent>
<EventType>Arousals|Arousals</EventType>
<EventConcept>Arousal resulting from respiratory effort|Arousal (RESP ARO)</EventConcept>
<Start>33060.7</Start>
<Duration>13.6</Duration>
<SignalLocation>C3</SignalLocation>
</ScoredEvent>
<ScoredEvent>
<EventType>Respiratory|Respiratory</EventType>
<EventConcept>Hypopnea|Hypopnea</EventConcept>
<Start>33190.2</Start>
<Duration>20.2</Duration>
<SignalLocation>ABDO EFFORT</SignalLocation>
</ScoredEvent>
<ScoredEvent>
<EventType>Arousals|Arousals</EventType>
<EventConcept>Arousal resulting from respiratory effort|Arousal (RESP ARO)</EventConcept>
<Start>33243.1</Start>
<Duration>26.7</Duration>
<SignalLocation>C3</SignalLocation>
</ScoredEvent>
<ScoredEvent>
<EventType>Arousals|Arousals</EventType>
<EventConcept>Arousal resulting from respiratory effort|Arousal (RESP ARO)</EventConcept>
<Start>33623.8</Start>
<Duration>6.2</Duration>
<SignalLocation>C3</SignalLocation>
</ScoredEvent>
<ScoredEvent>
<EventType>Respiratory|Respiratory</EventType>
<EventConcept>SpO2 artifact|SpO2 artifact</EventConcept>
<Start>33643</Start>
<Duration>4</Duration>
<SignalLocation>SaO2</SignalLocation>
</ScoredEvent>
<ScoredEvent>
<EventType>Stages|Stages</EventType>
<EventConcept>Wake|0</EventConcept>
<Start>0.0</Start>
<Duration>7860.0</Duration>
</ScoredEvent>
<ScoredEvent>
<EventType>Stages|Stages</EventType>
<EventConcept>Stage 1 sleep|1</EventConcept>
<Start>7860.0</Start>
<Duration>60.0</Duration>
</ScoredEvent>
<ScoredEvent>
<EventType>Stages|Stages</EventType>
<EventConcept>Stage 2 sleep|2</EventConcept>
<Start>7920.0</Start>
<Duration>120.0</Duration>
</ScoredEvent>
<ScoredEvent>
<EventType>Stages|Stages</EventType>
<EventConcept>Wake|0</EventConcept>
<Start>8040.0</Start>
<Duration>150.0</Duration>
</ScoredEvent>
<ScoredEvent>
<EventType>Stages|Stages</EventType>
<EventConcept>Stage 2 sleep|2</EventConcept>
<Start>8190.0</Start>
<Duration>210.0</Duration>
</ScoredEvent>
<ScoredEvent>
<EventType>Stages|Stages</EventType>
<EventConcept>Wake|0</EventConcept>
<Start>8400.0</Start>
<Duration>30.0</Duration>
</ScoredEvent>
<ScoredEvent>
<EventType>Stages|Stages</EventType>
<EventConcept>Stage 2 sleep|2</EventConcept>
<Start>8430.0</Start>
<Duration>570.0</Duration>
</ScoredEvent>
<ScoredEvent>
<EventType>Stages|Stages</EventType>
<EventConcept>Stage 3 sleep|3</EventConcept>
<Start>9000.0</Start>
<Duration>30.0</Duration>
</ScoredEvent>
<ScoredEvent>
<EventType>Stages|Stages</EventType>
<EventConcept>Stage 2 sleep|2</EventConcept>
<Start>9030.0</Start>
<Duration>60.0</Duration>
</ScoredEvent>
<ScoredEvent>
<EventType>Stages|Stages</EventType>
<EventConcept>Stage 3 sleep|3</EventConcept>
<Start>9090.0</Start>
<Duration>240.0</Duration>
</ScoredEvent>
<ScoredEvent>
<EventType>Stages|Stages</EventType>
<EventConcept>Stage 2 sleep|2</EventConcept>
<Start>9330.0</Start>
<Duration>30.0</Duration>
</ScoredEvent>
<ScoredEvent>
<EventType>Stages|Stages</EventType>
<EventConcept>Stage 3 sleep|3</EventConcept>
<Start>9360.0</Start>
<Duration>120.0</Duration>
</ScoredEvent>
<ScoredEvent>
<EventType>Stages|Stages</EventType>
<EventConcept>Stage 2 sleep|2</EventConcept>
<Start>9480.0</Start>
<Duration>30.0</Duration>
</ScoredEvent>
<ScoredEvent>
<EventType>Stages|Stages</EventType>
<EventConcept>Stage 3 sleep|3</EventConcept>
<Start>9510.0</Start>
<Duration>90.0</Duration>
</ScoredEvent>
<ScoredEvent>
<EventType>Stages|Stages</EventType>
<EventConcept>Stage 2 sleep|2</EventConcept>
<Start>9600.0</Start>
<Duration>30.0</Duration>
</ScoredEvent>
<ScoredEvent>
<EventType>Stages|Stages</EventType>
<EventConcept>Wake|0</EventConcept>
<Start>9630.0</Start>
<Duration>840.0</Duration>
</ScoredEvent>
<ScoredEvent>
<EventType>Stages|Stages</EventType>
<EventConcept>Stage 1 sleep|1</EventConcept>
<Start>10470.0</Start>
<Duration>30.0</Duration>
</ScoredEvent>
<ScoredEvent>
<EventType>Stages|Stages</EventType>
<EventConcept>Stage 2 sleep|2</EventConcept>
<Start>10500.0</Start>
<Duration>1410.0</Duration>
</ScoredEvent>
<ScoredEvent>
<EventType>Stages|Stages</EventType>
<EventConcept>Wake|0</EventConcept>
<Start>11910.0</Start>
<Duration>30.0</Duration>
</ScoredEvent>
<ScoredEvent>
<EventType>Stages|Stages</EventType>
<EventConcept>Stage 1 sleep|1</EventConcept>
<Start>11940.0</Start>
<Duration>30.0</Duration>
</ScoredEvent>
<ScoredEvent>
<EventType>Stages|Stages</EventType>
<EventConcept>Wake|0</EventConcept>
<Start>11970.0</Start>
<Duration>420.0</Duration>
</ScoredEvent>
<ScoredEvent>
<EventType>Stages|Stages</EventType>
<EventConcept>Stage 1 sleep|1</EventConcept>
<Start>12390.0</Start>
<Duration>30.0</Duration>
</ScoredEvent>
<ScoredEvent>
<EventType>Stages|Stages</EventType>
<EventConcept>Stage 2 sleep|2</EventConcept>
<Start>12420.0</Start>
<Duration>90.0</Duration>
</ScoredEvent>
<ScoredEvent>
<EventType>Stages|Stages</EventType>
<EventConcept>Wake|0</EventConcept>
<Start>12510.0</Start>
<Duration>180.0</Duration>
</ScoredEvent>
<ScoredEvent>
<EventType>Stages|Stages</EventType>
<EventConcept>Stage 2 sleep|2</EventConcept>
<Start>12690.0</Start>
<Duration>930.0</Duration>
</ScoredEvent>
<ScoredEvent>
<EventType>Stages|Stages</EventType>
<EventConcept>Wake|0</EventConcept>
<Start>13620.0</Start>
<Duration>30.0</Duration>
</ScoredEvent>
<ScoredEvent>
<EventType>Stages|Stages</EventType>
<EventConcept>Stage 2 sleep|2</EventConcept>
<Start>13650.0</Start>
<Duration>630.0</Duration>
</ScoredEvent>
<ScoredEvent>
<EventType>Stages|Stages</EventType>
<EventConcept>Stage 3 sleep|3</EventConcept>
<Start>14280.0</Start>
<Duration>90.0</Duration>
</ScoredEvent>
<ScoredEvent>
<EventType>Stages|Stages</EventType>
<EventConcept>Stage 2 sleep|2</EventConcept>
<Start>14370.0</Start>
<Duration>30.0</Duration>
</ScoredEvent>
<ScoredEvent>
<EventType>Stages|Stages</EventType>
<EventConcept>Stage 3 sleep|3</EventConcept>
<Start>14400.0</Start>
<Duration>900.0</Duration>
</ScoredEvent>
<ScoredEvent>
<EventType>Stages|Stages</EventType>
<EventConcept>Wake|0</EventConcept>
<Start>15300.0</Start>
<Duration>30.0</Duration>
</ScoredEvent>
<ScoredEvent>
<EventType>Stages|Stages</EventType>
<EventConcept>Stage 2 sleep|2</EventConcept>
<Start>15330.0</Start>
<Duration>30.0</Duration>
</ScoredEvent>
<ScoredEvent>
<EventType>Stages|Stages</EventType>
<EventConcept>Wake|0</EventConcept>
<Start>15360.0</Start>
<Duration>30.0</Duration>
</ScoredEvent>
<ScoredEvent>
<EventType>Stages|Stages</EventType>
<EventConcept>Stage 2 sleep|2</EventConcept>
<Start>15390.0</Start>
<Duration>450.0</Duration>
</ScoredEvent>
<ScoredEvent>
<EventType>Stages|Stages</EventType>
<EventConcept>Wake|0</EventConcept>
<Start>15840.0</Start>
<Duration>90.0</Duration>
</ScoredEvent>
<ScoredEvent>
<EventType>Stages|Stages</EventType>
<EventConcept>Stage 1 sleep|1</EventConcept>
<Start>15930.0</Start>
<Duration>30.0</Duration>
</ScoredEvent>
<ScoredEvent>
<EventType>Stages|Stages</EventType>
<EventConcept>Stage 2 sleep|2</EventConcept>
<Start>15960.0</Start>
<Duration>450.0</Duration>
</ScoredEvent>
<ScoredEvent>
<EventType>Stages|Stages</EventType>
<EventConcept>Wake|0</EventConcept>
<Start>16410.0</Start>
<Duration>510.0</Duration>
</ScoredEvent>
<ScoredEvent>
<EventType>Stages|Stages</EventType>
<EventConcept>Stage 1 sleep|1</EventConcept>
<Start>16920.0</Start>
<Duration>60.0</Duration>
</ScoredEvent>
<ScoredEvent>
<EventType>Stages|Stages</EventType>
<EventConcept>Stage 2 sleep|2</EventConcept>
<Start>16980.0</Start>
<Duration>90.0</Duration>
</ScoredEvent>
<ScoredEvent>
<EventType>Stages|Stages</EventType>
<EventConcept>Wake|0</EventConcept>
<Start>17070.0</Start>
<Duration>90.0</Duration>
</ScoredEvent>
<ScoredEvent>
<EventType>Stages|Stages</EventType>
<EventConcept>Stage 1 sleep|1</EventConcept>
<Start>17160.0</Start>
<Duration>30.0</Duration>
</ScoredEvent>
<ScoredEvent>
<EventType>Stages|Stages</EventType>
<EventConcept>Stage 2 sleep|2</EventConcept>
<Start>17190.0</Start>
<Duration>270.0</Duration>
</ScoredEvent>
<ScoredEvent>
<EventType>Stages|Stages</EventType>
<EventConcept>Wake|0</EventConcept>
<Start>17460.0</Start>
<Duration>30.0</Duration>
</ScoredEvent>
<ScoredEvent>
<EventType>Stages|Stages</EventType>
<EventConcept>Stage 2 sleep|2</EventConcept>
<Start>17490.0</Start>
<Duration>30.0</Duration>
</ScoredEvent>
<ScoredEvent>
<EventType>Stages|Stages</EventType>
<EventConcept>Wake|0</EventConcept>
<Start>17520.0</Start>
<Duration>30.0</Duration>
</ScoredEvent>
<ScoredEvent>
<EventType>Stages|Stages</EventType>
<EventConcept>Stage 2 sleep|2</EventConcept>
<Start>17550.0</Start>
<Duration>30.0</Duration>
</ScoredEvent>
<ScoredEvent>
<EventType>Stages|Stages</EventType>
<EventConcept>Wake|0</EventConcept>
<Start>17580.0</Start>
<Duration>30.0</Duration>
</ScoredEvent>
<ScoredEvent>
<EventType>Stages|Stages</EventType>
<EventConcept>Stage 1 sleep|1</EventConcept>
<Start>17610.0</Start>
<Duration>30.0</Duration>
</ScoredEvent>
<ScoredEvent>
<EventType>Stages|Stages</EventType>
<EventConcept>Stage 2 sleep|2</EventConcept>
<Start>17640.0</Start>
<Duration>1290.0</Duration>
</ScoredEvent>
<ScoredEvent>
<EventType>Stages|Stages</EventType>
<EventConcept>Stage 3 sleep|3</EventConcept>
<Start>18930.0</Start>
<Duration>30.0</Duration>
</ScoredEvent>
<ScoredEvent>
<EventType>Stages|Stages</EventType>
<EventConcept>Stage 2 sleep|2</EventConcept>
<Start>18960.0</Start>
<Duration>60.0</Duration>
</ScoredEvent>
<ScoredEvent>
<EventType>Stages|Stages</EventType>
<EventConcept>Stage 3 sleep|3</EventConcept>
<Start>19020.0</Start>
<Duration>30.0</Duration>
</ScoredEvent>
<ScoredEvent>
<EventType>Stages|Stages</EventType>
<EventConcept>Stage 2 sleep|2</EventConcept>
<Start>19050.0</Start>
<Duration>30.0</Duration>
</ScoredEvent>
<ScoredEvent>
<EventType>Stages|Stages</EventType>
<EventConcept>Wake|0</EventConcept>
<Start>19080.0</Start>
<Duration>30.0</Duration>
</ScoredEvent>
<ScoredEvent>
<EventType>Stages|Stages</EventType>
<EventConcept>Stage 2 sleep|2</EventConcept>
<Start>19110.0</Start>
<Duration>2070.0</Duration>
</ScoredEvent>
<ScoredEvent>
<EventType>Stages|Stages</EventType>
<EventConcept>Stage 3 sleep|3</EventConcept>
<Start>21180.0</Start>
<Duration>30.0</Duration>
</ScoredEvent>
<ScoredEvent>
<EventType>Stages|Stages</EventType>
<EventConcept>Stage 2 sleep|2</EventConcept>
<Start>21210.0</Start>
<Duration>60.0</Duration>
</ScoredEvent>
<ScoredEvent>
<EventType>Stages|Stages</EventType>
<EventConcept>Stage 3 sleep|3</EventConcept>
<Start>21270.0</Start>
<Duration>30.0</Duration>
</ScoredEvent>
<ScoredEvent>
<EventType>Stages|Stages</EventType>
<EventConcept>Stage 2 sleep|2</EventConcept>
<Start>21300.0</Start>
<Duration>90.0</Duration>
</ScoredEvent>
<ScoredEvent>
<EventType>Stages|Stages</EventType>
<EventConcept>Stage 3 sleep|3</EventConcept>
<Start>21390.0</Start>
<Duration>30.0</Duration>
</ScoredEvent>
<ScoredEvent>
<EventType>Stages|Stages</EventType>
<EventConcept>Stage 2 sleep|2</EventConcept>
<Start>21420.0</Start>
<Duration>30.0</Duration>
</ScoredEvent>
<ScoredEvent>
<EventType>Stages|Stages</EventType>
<EventConcept>Stage 3 sleep|3</EventConcept>
<Start>21450.0</Start>
<Duration>30.0</Duration>
</ScoredEvent>
<ScoredEvent>
<EventType>Stages|Stages</EventType>
<EventConcept>Stage 2 sleep|2</EventConcept>
<Start>21480.0</Start>
<Duration>120.0</Duration>
</ScoredEvent>
<ScoredEvent>
<EventType>Stages|Stages</EventType>
<EventConcept>Stage 3 sleep|3</EventConcept>
<Start>21600.0</Start>
<Duration>30.0</Duration>
</ScoredEvent>
<ScoredEvent>
<EventType>Stages|Stages</EventType>
<EventConcept>Stage 2 sleep|2</EventConcept>
<Start>21630.0</Start>
<Duration>180.0</Duration>
</ScoredEvent>
<ScoredEvent>
<EventType>Stages|Stages</EventType>
<EventConcept>Stage 3 sleep|3</EventConcept>
<Start>21810.0</Start>
<Duration>30.0</Duration>
</ScoredEvent>
<ScoredEvent>
<EventType>Stages|Stages</EventType>
<EventConcept>Stage 2 sleep|2</EventConcept>
<Start>21840.0</Start>
<Duration>30.0</Duration>
</ScoredEvent>
<ScoredEvent>
<EventType>Stages|Stages</EventType>
<EventConcept>Stage 3 sleep|3</EventConcept>
<Start>21870.0</Start>
<Duration>30.0</Duration>
</ScoredEvent>
<ScoredEvent>
<EventType>Stages|Stages</EventType>
<EventConcept>Stage 2 sleep|2</EventConcept>
<Start>21900.0</Start>
<Duration>30.0</Duration>
</ScoredEvent>
<ScoredEvent>
<EventType>Stages|Stages</EventType>
<EventConcept>Stage 3 sleep|3</EventConcept>
<Start>21930.0</Start>
<Duration>30.0</Duration>
</ScoredEvent>
<ScoredEvent>
<EventType>Stages|Stages</EventType>
<EventConcept>Stage 2 sleep|2</EventConcept>
<Start>21960.0</Start>
<Duration>60.0</Duration>
</ScoredEvent>
<ScoredEvent>
<EventType>Stages|Stages</EventType>
<EventConcept>Stage 3 sleep|3</EventConcept>
<Start>22020.0</Start>
<Duration>30.0</Duration>
</ScoredEvent>
<ScoredEvent>
<EventType>Stages|Stages</EventType>
<EventConcept>Stage 2 sleep|2</EventConcept>
<Start>22050.0</Start>
<Duration>60.0</Duration>
</ScoredEvent>
<ScoredEvent>
<EventType>Stages|Stages</EventType>
<EventConcept>Stage 3 sleep|3</EventConcept>
<Start>22110.0</Start>
<Duration>30.0</Duration>
</ScoredEvent>
<ScoredEvent>
<EventType>Stages|Stages</EventType>
<EventConcept>Stage 2 sleep|2</EventConcept>
<Start>22140.0</Start>
<Duration>30.0</Duration>
</ScoredEvent>
<ScoredEvent>
<EventType>Stages|Stages</EventType>
<EventConcept>Stage 3 sleep|3</EventConcept>
<Start>22170.0</Start>
<Duration>60.0</Duration>
</ScoredEvent>
<ScoredEvent>
<EventType>Stages|Stages</EventType>
<EventConcept>Wake|0</EventConcept>
<Start>22230.0</Start>
<Duration>30.0</Duration>
</ScoredEvent>
<ScoredEvent>
<EventType>Stages|Stages</EventType>
<EventConcept>Stage 2 sleep|2</EventConcept>
<Start>22260.0</Start>
<Duration>30.0</Duration>
</ScoredEvent>
<ScoredEvent>
<EventType>Stages|Stages</EventType>
<EventConcept>Wake|0</EventConcept>
<Start>22290.0</Start>
<Duration>150.0</Duration>
</ScoredEvent>
<ScoredEvent>
<EventType>Stages|Stages</EventType>
<EventConcept>Stage 2 sleep|2</EventConcept>
<Start>22440.0</Start>
<Duration>660.0</Duration>
</ScoredEvent>
<ScoredEvent>
<EventType>Stages|Stages</EventType>
<EventConcept>Wake|0</EventConcept>
<Start>23100.0</Start>
<Duration>60.0</Duration>
</ScoredEvent>
<ScoredEvent>
<EventType>Stages|Stages</EventType>
<EventConcept>Stage 2 sleep|2</EventConcept>
<Start>23160.0</Start>
<Duration>900.0</Duration>
</ScoredEvent>
<ScoredEvent>
<EventType>Stages|Stages</EventType>
<EventConcept>Wake|0</EventConcept>
<Start>24060.0</Start>
<Duration>150.0</Duration>
</ScoredEvent>
<ScoredEvent>
<EventType>Stages|Stages</EventType>
<EventConcept>Stage 2 sleep|2</EventConcept>
<Start>24210.0</Start>
<Duration>690.0</Duration>
</ScoredEvent>
<ScoredEvent>
<EventType>Stages|Stages</EventType>
<EventConcept>Wake|0</EventConcept>
<Start>24900.0</Start>
<Duration>30.0</Duration>
</ScoredEvent>
<ScoredEvent>
<EventType>Stages|Stages</EventType>
<EventConcept>Stage 2 sleep|2</EventConcept>
<Start>24930.0</Start>
<Duration>30.0</Duration>
</ScoredEvent>
<ScoredEvent>
<EventType>Stages|Stages</EventType>
<EventConcept>Wake|0</EventConcept>
<Start>24960.0</Start>
<Duration>120.0</Duration>
</ScoredEvent>
<ScoredEvent>
<EventType>Stages|Stages</EventType>
<EventConcept>Stage 2 sleep|2</EventConcept>
<Start>25080.0</Start>
<Duration>840.0</Duration>
</ScoredEvent>
<ScoredEvent>
<EventType>Stages|Stages</EventType>
<EventConcept>Wake|0</EventConcept>
<Start>25920.0</Start>
<Duration>30.0</Duration>
</ScoredEvent>
<ScoredEvent>
<EventType>Stages|Stages</EventType>
<EventConcept>Stage 1 sleep|1</EventConcept>
<Start>25950.0</Start>
<Duration>30.0</Duration>
</ScoredEvent>
<ScoredEvent>
<EventType>Stages|Stages</EventType>
<EventConcept>Stage 2 sleep|2</EventConcept>
<Start>25980.0</Start>
<Duration>330.0</Duration>
</ScoredEvent>
<ScoredEvent>
<EventType>Stages|Stages</EventType>
<EventConcept>Wake|0</EventConcept>
<Start>26310.0</Start>
<Duration>120.0</Duration>
</ScoredEvent>
<ScoredEvent>
<EventType>Stages|Stages</EventType>
<EventConcept>Stage 1 sleep|1</EventConcept>
<Start>26430.0</Start>
<Duration>30.0</Duration>
</ScoredEvent>
<ScoredEvent>
<EventType>Stages|Stages</EventType>
<EventConcept>Stage 2 sleep|2</EventConcept>
<Start>26460.0</Start>
<Duration>30.0</Duration>
</ScoredEvent>
<ScoredEvent>
<EventType>Stages|Stages</EventType>
<EventConcept>Wake|0</EventConcept>
<Start>26490.0</Start>
<Duration>420.0</Duration>
</ScoredEvent>
<ScoredEvent>
<EventType>Stages|Stages</EventType>
<EventConcept>Stage 2 sleep|2</EventConcept>
<Start>26910.0</Start>
<Duration>150.0</Duration>
</ScoredEvent>
<ScoredEvent>
<EventType>Stages|Stages</EventType>
<EventConcept>Wake|0</EventConcept>
<Start>27060.0</Start>
<Duration>240.0</Duration>
</ScoredEvent>
<ScoredEvent>
<EventType>Stages|Stages</EventType>
<EventConcept>Stage 1 sleep|1</EventConcept>
<Start>27300.0</Start>
<Duration>240.0</Duration>
</ScoredEvent>
<ScoredEvent>
<EventType>Stages|Stages</EventType>
<EventConcept>Stage 2 sleep|2</EventConcept>
<Start>27540.0</Start>
<Duration>1590.0</Duration>
</ScoredEvent>
<ScoredEvent>
<EventType>Stages|Stages</EventType>
<EventConcept>Wake|0</EventConcept>
<Start>29130.0</Start>
<Duration>150.0</Duration>
</ScoredEvent>
<ScoredEvent>
<EventType>Stages|Stages</EventType>
<EventConcept>Stage 1 sleep|1</EventConcept>
<Start>29280.0</Start>
<Duration>30.0</Duration>
</ScoredEvent>
<ScoredEvent>
<EventType>Stages|Stages</EventType>
<EventConcept>Stage 2 sleep|2</EventConcept>
<Start>29310.0</Start>
<Duration>120.0</Duration>
</ScoredEvent>
<ScoredEvent>
<EventType>Stages|Stages</EventType>
<EventConcept>Wake|0</EventConcept>
<Start>29430.0</Start>
<Duration>30.0</Duration>
</ScoredEvent>
<ScoredEvent>
<EventType>Stages|Stages</EventType>
<EventConcept>Stage 1 sleep|1</EventConcept>
<Start>29460.0</Start>
<Duration>30.0</Duration>
</ScoredEvent>
<ScoredEvent>
<EventType>Stages|Stages</EventType>
<EventConcept>Stage 2 sleep|2</EventConcept>
<Start>29490.0</Start>
<Duration>180.0</Duration>
</ScoredEvent>
<ScoredEvent>
<EventType>Stages|Stages</EventType>
<EventConcept>Wake|0</EventConcept>
<Start>29670.0</Start>
<Duration>30.0</Duration>
</ScoredEvent>
<ScoredEvent>
<EventType>Stages|Stages</EventType>
<EventConcept>Stage 1 sleep|1</EventConcept>
<Start>29700.0</Start>
<Duration>120.0</Duration>
</ScoredEvent>
<ScoredEvent>
<EventType>Stages|Stages</EventType>
<EventConcept>Stage 2 sleep|2</EventConcept>
<Start>29820.0</Start>
<Duration>120.0</Duration>
</ScoredEvent>
<ScoredEvent>
<EventType>Stages|Stages</EventType>
<EventConcept>Wake|0</EventConcept>
<Start>29940.0</Start>
<Duration>60.0</Duration>
</ScoredEvent>
<ScoredEvent>
<EventType>Stages|Stages</EventType>
<EventConcept>Stage 1 sleep|1</EventConcept>
<Start>30000.0</Start>
<Duration>60.0</Duration>
</ScoredEvent>
<ScoredEvent>
<EventType>Stages|Stages</EventType>
<EventConcept>Stage 2 sleep|2</EventConcept>
<Start>30060.0</Start>
<Duration>120.0</Duration>
</ScoredEvent>
<ScoredEvent>
<EventType>Stages|Stages</EventType>
<EventConcept>Wake|0</EventConcept>
<Start>30180.0</Start>
<Duration>30.0</Duration>
</ScoredEvent>
<ScoredEvent>
<EventType>Stages|Stages</EventType>
<EventConcept>Stage 1 sleep|1</EventConcept>
<Start>30210.0</Start>
<Duration>60.0</Duration>
</ScoredEvent>
<ScoredEvent>
<EventType>Stages|Stages</EventType>
<EventConcept>Stage 2 sleep|2</EventConcept>
<Start>30270.0</Start>
<Duration>510.0</Duration>
</ScoredEvent>
<ScoredEvent>
<EventType>Stages|Stages</EventType>
<EventConcept>Wake|0</EventConcept>
<Start>30780.0</Start>
<Duration>360.0</Duration>
</ScoredEvent>
<ScoredEvent>
<EventType>Stages|Stages</EventType>
<EventConcept>Stage 1 sleep|1</EventConcept>
<Start>31140.0</Start>
<Duration>60.0</Duration>
</ScoredEvent>
<ScoredEvent>
<EventType>Stages|Stages</EventType>
<EventConcept>Stage 2 sleep|2</EventConcept>
<Start>31200.0</Start>
<Duration>30.0</Duration>
</ScoredEvent>
<ScoredEvent>
<EventType>Stages|Stages</EventType>
<EventConcept>Wake|0</EventConcept>
<Start>31230.0</Start>
<Duration>60.0</Duration>
</ScoredEvent>
<ScoredEvent>
<EventType>Stages|Stages</EventType>
<EventConcept>Stage 1 sleep|1</EventConcept>
<Start>31290.0</Start>
<Duration>30.0</Duration>
</ScoredEvent>
<ScoredEvent>
<EventType>Stages|Stages</EventType>
<EventConcept>Stage 2 sleep|2</EventConcept>
<Start>31320.0</Start>
<Duration>570.0</Duration>
</ScoredEvent>
<ScoredEvent>
<EventType>Stages|Stages</EventType>
<EventConcept>Wake|0</EventConcept>
<Start>31890.0</Start>
<Duration>30.0</Duration>
</ScoredEvent>
<ScoredEvent>
<EventType>Stages|Stages</EventType>
<EventConcept>Stage 1 sleep|1</EventConcept>
<Start>31920.0</Start>
<Duration>30.0</Duration>
</ScoredEvent>
<ScoredEvent>
<EventType>Stages|Stages</EventType>
<EventConcept>Stage 2 sleep|2</EventConcept>
<Start>31950.0</Start>
<Duration>30.0</Duration>
</ScoredEvent>
<ScoredEvent>
<EventType>Stages|Stages</EventType>
<EventConcept>Wake|0</EventConcept>
<Start>31980.0</Start>
<Duration>90.0</Duration>
</ScoredEvent>
<ScoredEvent>
<EventType>Stages|Stages</EventType>
<EventConcept>Stage 1 sleep|1</EventConcept>
<Start>32070.0</Start>
<Duration>60.0</Duration>
</ScoredEvent>
<ScoredEvent>
<EventType>Stages|Stages</EventType>
<EventConcept>Stage 2 sleep|2</EventConcept>
<Start>32130.0</Start>
<Duration>390.0</Duration>
</ScoredEvent>
<ScoredEvent>
<EventType>Stages|Stages</EventType>
<EventConcept>Wake|0</EventConcept>
<Start>32520.0</Start>
<Duration>90.0</Duration>
</ScoredEvent>
<ScoredEvent>
<EventType>Stages|Stages</EventType>
<EventConcept>Stage 1 sleep|1</EventConcept>
<Start>32610.0</Start>
<Duration>60.0</Duration>
</ScoredEvent>
<ScoredEvent>
<EventType>Stages|Stages</EventType>
<EventConcept>Wake|0</EventConcept>
<Start>32670.0</Start>
<Duration>30.0</Duration>
</ScoredEvent>
<ScoredEvent>
<EventType>Stages|Stages</EventType>
<EventConcept>Stage 1 sleep|1</EventConcept>
<Start>32700.0</Start>
<Duration>240.0</Duration>
</ScoredEvent>
<ScoredEvent>
<EventType>Stages|Stages</EventType>
<EventConcept>Wake|0</EventConcept>
<Start>32940.0</Start>
<Duration>90.0</Duration>
</ScoredEvent>
<ScoredEvent>
<EventType>Stages|Stages</EventType>
<EventConcept>Stage 1 sleep|1</EventConcept>
<Start>33030.0</Start>
<Duration>90.0</Duration>
</ScoredEvent>
<ScoredEvent>
<EventType>Stages|Stages</EventType>
<EventConcept>Stage 2 sleep|2</EventConcept>
<Start>33120.0</Start>
<Duration>120.0</Duration>
</ScoredEvent>
<ScoredEvent>
<EventType>Stages|Stages</EventType>
<EventConcept>Wake|0</EventConcept>
<Start>33240.0</Start>
<Duration>120.0</Duration>
</ScoredEvent>
<ScoredEvent>
<EventType>Stages|Stages</EventType>
<EventConcept>Stage 1 sleep|1</EventConcept>
<Start>33360.0</Start>
<Duration>60.0</Duration>
</ScoredEvent>
<ScoredEvent>
<EventType>Stages|Stages</EventType>
<EventConcept>Stage 2 sleep|2</EventConcept>
<Start>33420.0</Start>
<Duration>210.0</Duration>
</ScoredEvent>
<ScoredEvent>
<EventType>Stages|Stages</EventType>
<EventConcept>Wake|0</EventConcept>
<Start>33630.0</Start>
<Duration>120.0</Duration>
</ScoredEvent>
<ScoredEvent>
<EventType>Stages|Stages</EventType>
<EventConcept>Stage 1 sleep|1</EventConcept>
<Start>33750.0</Start>
<Duration>60.0</Duration>
</ScoredEvent>
<ScoredEvent>
<EventType>Stages|Stages</EventType>
<EventConcept>Stage 2 sleep|2</EventConcept>
<Start>33810.0</Start>
<Duration>30.0</Duration>
</ScoredEvent>
</ScoredEvents>
</PSGAnnotation>
